[
  {
    "component": "header",
    "variant": 1,
    "value": "opening_key1"
  },
  {
    "component": "header",
    "variant": 4,
    "value": "opening_key2"
  },
  {
    "component": "text",
    "value": "opening_key3",
    "decoration": {
      "type": "number",
      "value": null
    }
  },
  {
    "component": "text",
    "value": "opening_key4",
    "decoration": {
      "type": "number",
      "value": null
    }
  },
  {
    "component": "text",
    "value": "opening_key5",
    "decoration": {
      "type": "number",
      "value": null
    }
  },
  {
    "component": "text",
    "value": "opening_key6",
    "decoration": {
      "type": "number",
      "value": null
    }
  },
  {
    "component": "header",
    "variant": 4,
    "value": "opening_key7"
  },
  {
    "component": "text",
    "value": "opening_key8",
    "decoration": {
      "type": "number",
      "value": null
    }
  },
  {
    "component": "text",
    "value": "opening_key9",
    "decoration": {
      "type": "number",
      "value": null
    }
  },
  {
    "component": "header",
    "variant": 1,
    "value": "opening_key10"
  },
  {
    "component": "header",
    "variant": 3,
    "value": "opening_key11"
  },
  {
    "component": "text",
    "value": "opening_key12"
  },
  {
    "component": "text",
    "value": "opening_key13",
    "decoration": {
      "type": "number",
      "value": null
    }
  },
  {
    "component": "text",
    "value": "opening_key14",
    "decoration": {
      "type": "number",
      "value": null
    }
  },
  {
    "component": "text",
    "value": "opening_key15",
    "decoration": {
      "type": "number",
      "value": null
    }
  },
  {
    "component": "text",
    "value": "opening_key16",
    "decoration": {
      "type": "number",
      "value": null
    }
  },
  {
    "component": "text",
    "value": "opening_key17",
    "decoration": {
      "type": "number",
      "value": null
    }
  },
  {
    "component": "text",
    "value": "opening_key18",
    "decoration": {
      "type": "number",
      "value": null
    }
  },
  {
    "component": "text",
    "value": "opening_key19",
    "decoration": {
      "type": "number",
      "value": null
    }
  },
  {
    "component": "text",
    "value": "opening_key20",
    "decoration": {
      "type": "number",
      "value": null
    }
  },
  {
    "component": "text",
    "value": "opening_key21",
    "decoration": {
      "type": "number",
      "value": null
    }
  },
  {
    "component": "text",
    "value": "opening_key22",
    "decoration": {
      "type": "number",
      "value": null
    }
  },
  {
    "component": "text",
    "value": "opening_key23",
    "decoration": {
      "type": "number",
      "value": null
    }
  },
  {
    "component": "header",
    "variant": 3,
    "value": "opening_key24"
  },
  {
    "component": "text",
    "value": "opening_key25",
    "decoration": {
      "type": "number",
      "value": null
    }
  },
  {
    "component": "text",
    "value": "opening_key26",
    "decoration": {
      "type": "number",
      "value": null
    }
  },
  {
    "component": "text",
    "value": "opening_key27",
    "decoration": {
      "type": "number",
      "value": null
    }
  },
  {
    "component": "text",
    "value": "opening_key28",
    "decoration": {
      "type": "number",
      "value": null
    }
  },
  {
    "component": "text",
    "value": "opening_key29",
    "decoration": {
      "type": "number",
      "value": null
    }
  },
  {
    "component": "text",
    "value": "opening_key30",
    "decoration": {
      "type": "number",
      "value": null
    }
  }
]