{
	"todo_key1": "name: Pending To-Dos (for course creators)\n",
	"todo_key2": "# Pending Tasks\n\n\n",
	"todo_key3": "**Yogendra** Simple Series (Alternative Series 1) Video\n",
	"todo_key4": "**Pavan** Simple Series (Alternative Series 2) Video\n",
	"todo_key5": "**Yogendra** Factorial video\n",
	"todo_key6": "**Satyam** Sum of a list solution video\n",
	"todo_key7": "**Yogendra** palindrome `string` solution video\n",
	"todo_key8": "~~**Satyam** fibonacci series solution Video~~\n",
	"todo_key9": "**Pralhad** fibonacci series advanced solution Video\n",
	"todo_key10": "**Pralhad** binary search solution Video\n",
	"todo_key11": "**Pavan** calculate solution Video\n",
	"todo_key12": "**Pavan/Pralhad** nested lists\n"
}