[
  {
    "component": "text",
    "value": "Assignment-operators_key1"
  },
  {
    "component": "table",
    "value": [
      {
        "header": "Assignment-operators_key2",
        "items": [
          "Assignment-operators_key3",
          "Assignment-operators_key4",
          "Assignment-operators_key5",
          "Assignment-operators_key6",
          "Assignment-operators_key7",
          "Assignment-operators_key8",
          "Assignment-operators_key9"
        ]
      },
      {
        "header": "Assignment-operators_key10",
        "items": [
          "Assignment-operators_key11",
          "Assignment-operators_key12",
          "Assignment-operators_key13",
          "Assignment-operators_key14",
          "Assignment-operators_key15",
          "Assignment-operators_key16",
          "Assignment-operators_key17"
        ]
      },
      {
        "header": "Assignment-operators_key18",
        "items": [
          "Assignment-operators_key19",
          "Assignment-operators_key20",
          "Assignment-operators_key21",
          "Assignment-operators_key22",
          "Assignment-operators_key23",
          "Assignment-operators_key24",
          "Assignment-operators_key25"
        ]
      }
    ]
  },
  {
    "component": "header",
    "variant": 2,
    "value": "Assignment-operators_key26"
  },
  {
    "component": "code",
    "type": "javascript",
    "title": "",
    "value": "var x = 5, y = 10, z = 15;<br><br>console.log(x = y);<br>console.log( x+= 1);<br>console.log(x -= 1);<br>console.log(x *= 5);<br>console.log(x /= 5);<br>console.log(x %= 2);"
  },
  {
    "component": "code",
    "type": "javascript",
    "title": "solution",
    "value": "10<br>11<br>10<br>50<br>10<br>0"
  }
]