[
  {
    "component": "header",
    "variant": 1,
    "value": "pattern-matching-with-regular-expressions_key1"
  },
  {
    "component": "text",
    "value": "pattern-matching-with-regular-expressions_key2"
  },
  {
    "component": "text",
    "value": "pattern-matching-with-regular-expressions_key3"
  },
  {
    "component": "text",
    "value": "pattern-matching-with-regular-expressions_key4"
  },
  {
    "component": "text",
    "value": "pattern-matching-with-regular-expressions_key5"
  },
  {
    "component": "header",
    "variant": 1,
    "value": "pattern-matching-with-regular-expressions_key6"
  },
  {
    "component": "text",
    "value": "pattern-matching-with-regular-expressions_key7"
  },
  {
    "component": "text",
    "value": "pattern-matching-with-regular-expressions_key8"
  },
  {
    "component": "code",
    "type": "python",
    "title": "",
    "value": "def isPhoneNumber(text):<br>❶     if len(text) != 12:<br>           return False<br>       for i in range(0, 3):<br>❷         if not text[i].isdecimal():<br>               return False<br>❸     if text[3] != '-':<br>           return False<br>       for i in range(4, 7):<br>❹         if not text[i].isdecimal():<br>               return False<br>❺     if text[7] != '-':<br>           return False<br>       for i in range(8, 12):<br>❻         if not text[i].isdecimal():<br>               return False<br>❼     return True<br><br>   print('415-555-4242 is a phone number:')<br>   print(isPhoneNumber('415-555-4242'))<br>   print('Moshi moshi is a phone number:')<br>   print(isPhoneNumber('Moshi moshi'))"
  },
  {
    "component": "text",
    "value": "pattern-matching-with-regular-expressions_key9"
  },
  {
    "component": "code",
    "type": "python",
    "title": "",
    "value": "415-555-4242 is a phone number:<br>True<br>Moshi moshi is a phone number:<br>False"
  },
  {
    "component": "text",
    "value": "pattern-matching-with-regular-expressions_key10"
  },
  {
    "component": "text",
    "value": "pattern-matching-with-regular-expressions_key11"
  },
  {
    "component": "text",
    "value": "pattern-matching-with-regular-expressions_key12"
  },
  {
    "component": "code",
    "type": "python",
    "title": "",
    "value": "message = 'Call me at 415-555-1011 tomorrow. 415-555-9999 is my office.'<br>   for i in range(len(message)):<br>❶     chunk = message[i:i+12]<br>❷     if isPhoneNumber(chunk):<br>         print('Phone number found: ' + chunk)<br>   print('Done')"
  },
  {
    "component": "text",
    "value": "pattern-matching-with-regular-expressions_key13"
  },
  {
    "component": "text",
    "value": "pattern-matching-with-regular-expressions_key14"
  },
  {
    "component": "text",
    "value": "pattern-matching-with-regular-expressions_key15"
  },
  {
    "component": "text",
    "value": "pattern-matching-with-regular-expressions_key16"
  },
  {
    "component": "text",
    "value": "pattern-matching-with-regular-expressions_key17"
  }
]