[
	{
		"component": "header",
		"variant": 1,
		"value": "Level Seven"
	},
	{
		"component": "text",
		"value": "cross",
		"decoration": {
			"type": "bullet"
		}
	},
	{
		"component": "text",
		"value": "speak",
		"decoration": {
			"type": "bullet"
		}
	},
	{
		"component": "text",
		"value": "solve",
		"decoration": {
			"type": "bullet"
		}
	},
	{
		"component": "text",
		"value": "appear",
		"decoration": {
			"type": "bullet"
		}
	},
	{
		"component": "text",
		"value": "metal",
		"decoration": {
			"type": "bullet"
		}
	},
	{
		"component": "text",
		"value": "son",
		"decoration": {
			"type": "bullet"
		}
	},
	{
		"component": "text",
		"value": "either",
		"decoration": {
			"type": "bullet"
		}
	},
	{
		"component": "text",
		"value": "ice",
		"decoration": {
			"type": "bullet"
		}
	},
	{
		"component": "text",
		"value": "sleep",
		"decoration": {
			"type": "bullet"
		}
	},
	{
		"component": "text",
		"value": "village",
		"decoration": {
			"type": "bullet"
		}
	},
	{
		"component": "text",
		"value": "factors",
		"decoration": {
			"type": "bullet"
		}
	},
	{
		"component": "text",
		"value": "result",
		"decoration": {
			"type": "bullet"
		}
	},
	{
		"component": "text",
		"value": "jumped",
		"decoration": {
			"type": "bullet"
		}
	},
	{
		"component": "text",
		"value": "snow",
		"decoration": {
			"type": "bullet"
		}
	},
	{
		"component": "text",
		"value": "ride",
		"decoration": {
			"type": "bullet"
		}
	},
	{
		"component": "text",
		"value": "care",
		"decoration": {
			"type": "bullet"
		}
	},
	{
		"component": "text",
		"value": "floor",
		"decoration": {
			"type": "bullet"
		}
	},
	{
		"component": "text",
		"value": "hill",
		"decoration": {
			"type": "bullet"
		}
	},
	{
		"component": "text",
		"value": "pushed",
		"decoration": {
			"type": "bullet"
		}
	},
	{
		"component": "text",
		"value": "baby",
		"decoration": {
			"type": "bullet"
		}
	},
	{
		"component": "text",
		"value": "buy",
		"decoration": {
			"type": "bullet"
		}
	},
	{
		"component": "text",
		"value": "century",
		"decoration": {
			"type": "bullet"
		}
	},
	{
		"component": "text",
		"value": "outside",
		"decoration": {
			"type": "bullet"
		}
	},
	{
		"component": "text",
		"value": "everything",
		"decoration": {
			"type": "bullet"
		}
	},
	{
		"component": "text",
		"value": "tall",
		"decoration": {
			"type": "bullet"
		}
	},
	{
		"component": "text",
		"value": "already",
		"decoration": {
			"type": "bullet"
		}
	},
	{
		"component": "text",
		"value": "instead",
		"decoration": {
			"type": "bullet"
		}
	},
	{
		"component": "text",
		"value": "phrase",
		"decoration": {
			"type": "bullet"
		}
	},
	{
		"component": "text",
		"value": "soil",
		"decoration": {
			"type": "bullet"
		}
	},
	{
		"component": "text",
		"value": "bed",
		"decoration": {
			"type": "bullet"
		}
	},
	{
		"component": "text",
		"value": "copy",
		"decoration": {
			"type": "bullet"
		}
	},
	{
		"component": "text",
		"value": "free",
		"decoration": {
			"type": "bullet"
		}
	},
	{
		"component": "text",
		"value": "hope",
		"decoration": {
			"type": "bullet"
		}
	},
	{
		"component": "text",
		"value": "spring",
		"decoration": {
			"type": "bullet"
		}
	},
	{
		"component": "text",
		"value": "case",
		"decoration": {
			"type": "bullet"
		}
	},
	{
		"component": "text",
		"value": "laughed",
		"decoration": {
			"type": "bullet"
		}
	},
	{
		"component": "text",
		"value": "nation",
		"decoration": {
			"type": "bullet"
		}
	},
	{
		"component": "text",
		"value": "quite",
		"decoration": {
			"type": "bullet"
		}
	},
	{
		"component": "text",
		"value": "type",
		"decoration": {
			"type": "bullet"
		}
	},
	{
		"component": "text",
		"value": "themselves",
		"decoration": {
			"type": "bullet"
		}
	},
	{
		"component": "text",
		"value": "temperature",
		"decoration": {
			"type": "bullet"
		}
	},
	{
		"component": "text",
		"value": "bright",
		"decoration": {
			"type": "bullet"
		}
	},
	{
		"component": "text",
		"value": "lead",
		"decoration": {
			"type": "bullet"
		}
	},
	{
		"component": "text",
		"value": "everyone",
		"decoration": {
			"type": "bullet"
		}
	},
	{
		"component": "text",
		"value": "method",
		"decoration": {
			"type": "bullet"
		}
	},
	{
		"component": "text",
		"value": "section",
		"decoration": {
			"type": "bullet"
		}
	},
	{
		"component": "text",
		"value": "lake",
		"decoration": {
			"type": "bullet"
		}
	},
	{
		"component": "text",
		"value": "iron",
		"decoration": {
			"type": "bullet"
		}
	},
	{
		"component": "text",
		"value": "within",
		"decoration": {
			"type": "bullet"
		}
	},
	{
		"component": "text",
		"value": "dictionary",
		"decoration": {
			"type": "bullet"
		}
	},
	{
		"component": "text",
		"value": "hair",
		"decoration": {
			"type": "bullet"
		}
	},
	{
		"component": "text",
		"value": "age",
		"decoration": {
			"type": "bullet"
		}
	},
	{
		"component": "text",
		"value": "amount",
		"decoration": {
			"type": "bullet"
		}
	},
	{
		"component": "text",
		"value": "scale",
		"decoration": {
			"type": "bullet"
		}
	},
	{
		"component": "text",
		"value": "pounds",
		"decoration": {
			"type": "bullet"
		}
	},
	{
		"component": "text",
		"value": "although",
		"decoration": {
			"type": "bullet"
		}
	},
	{
		"component": "text",
		"value": "per",
		"decoration": {
			"type": "bullet"
		}
	},
	{
		"component": "text",
		"value": "broken",
		"decoration": {
			"type": "bullet"
		}
	},
	{
		"component": "text",
		"value": "moment",
		"decoration": {
			"type": "bullet"
		}
	},
	{
		"component": "text",
		"value": "tiny",
		"decoration": {
			"type": "bullet"
		}
	},
	{
		"component": "text",
		"value": "possible",
		"decoration": {
			"type": "bullet"
		}
	},
	{
		"component": "text",
		"value": "gold",
		"decoration": {
			"type": "bullet"
		}
	},
	{
		"component": "text",
		"value": "milk",
		"decoration": {
			"type": "bullet"
		}
	},
	{
		"component": "text",
		"value": "quiet",
		"decoration": {
			"type": "bullet"
		}
	},
	{
		"component": "text",
		"value": "natural",
		"decoration": {
			"type": "bullet"
		}
	},
	{
		"component": "text",
		"value": "lot",
		"decoration": {
			"type": "bullet"
		}
	},
	{
		"component": "text",
		"value": "stone",
		"decoration": {
			"type": "bullet"
		}
	},
	{
		"component": "text",
		"value": "act",
		"decoration": {
			"type": "bullet"
		}
	},
	{
		"component": "text",
		"value": "build",
		"decoration": {
			"type": "bullet"
		}
	},
	{
		"component": "text",
		"value": "middle",
		"decoration": {
			"type": "bullet"
		}
	},
	{
		"component": "text",
		"value": "speed",
		"decoration": {
			"type": "bullet"
		}
	},
	{
		"component": "text",
		"value": "count",
		"decoration": {
			"type": "bullet"
		}
	},
	{
		"component": "text",
		"value": "consonant",
		"decoration": {
			"type": "bullet"
		}
	},
	{
		"component": "text",
		"value": "someone",
		"decoration": {
			"type": "bullet"
		}
	},
	{
		"component": "text",
		"value": "sail",
		"decoration": {
			"type": "bullet"
		}
	},
	{
		"component": "text",
		"value": "rolled",
		"decoration": {
			"type": "bullet"
		}
	},
	{
		"component": "text",
		"value": "bear",
		"decoration": {
			"type": "bullet"
		}
	},
	{
		"component": "text",
		"value": "wonder",
		"decoration": {
			"type": "bullet"
		}
	},
	{
		"component": "text",
		"value": "smiled",
		"decoration": {
			"type": "bullet"
		}
	},
	{
		"component": "text",
		"value": "angle",
		"decoration": {
			"type": "bullet"
		}
	},
	{
		"component": "text",
		"value": "fraction",
		"decoration": {
			"type": "bullet"
		}
	},
	{
		"component": "text",
		"value": "Africa",
		"decoration": {
			"type": "bullet"
		}
	},
	{
		"component": "text",
		"value": "killed",
		"decoration": {
			"type": "bullet"
		}
	},
	{
		"component": "text",
		"value": "melody",
		"decoration": {
			"type": "bullet"
		}
	},
	{
		"component": "text",
		"value": "bottom",
		"decoration": {
			"type": "bullet"
		}
	},
	{
		"component": "text",
		"value": "trip",
		"decoration": {
			"type": "bullet"
		}
	},
	{
		"component": "text",
		"value": "hole",
		"decoration": {
			"type": "bullet"
		}
	},
	{
		"component": "text",
		"value": "poor",
		"decoration": {
			"type": "bullet"
		}
	},
	{
		"component": "text",
		"value": "let’s",
		"decoration": {
			"type": "bullet"
		}
	},
	{
		"component": "text",
		"value": "fight",
		"decoration": {
			"type": "bullet"
		}
	},
	{
		"component": "text",
		"value": "surprise",
		"decoration": {
			"type": "bullet"
		}
	},
	{
		"component": "text",
		"value": "French",
		"decoration": {
			"type": "bullet"
		}
	},
	{
		"component": "text",
		"value": "died",
		"decoration": {
			"type": "bullet"
		}
	},
	{
		"component": "text",
		"value": "beat",
		"decoration": {
			"type": "bullet"
		}
	},
	{
		"component": "text",
		"value": "exactly",
		"decoration": {
			"type": "bullet"
		}
	},
	{
		"component": "text",
		"value": "remain",
		"decoration": {
			"type": "bullet"
		}
	},
	{
		"component": "text",
		"value": "dress",
		"decoration": {
			"type": "bullet"
		}
	},
	{
		"component": "text",
		"value": "cat",
		"decoration": {
			"type": "bullet"
		}
	},
	{
		"component": "text",
		"value": "couldn’t",
		"decoration": {
			"type": "bullet"
		}
	},
	{
		"component": "text",
		"value": "fingers",
		"decoration": {
			"type": "bullet"
		}
	}
]