[
	{
		"component": "text",
		"value": "[<br>    {<br>        \"component\": \"header\",<br>        \"variant\": 1,<br>        \"value\": \"Aap yeh videos dekhein:\"<br>    },<br>    {<br>        \"component\": \"header\",<br>        \"variant\": 2,<br>        \"value\": \"Introduction of SAAS\"<br>    },<br>    {<br>        \"component\": \"text\",<br>        \"value\": \"Eska pura nam <span style=\\\"color: #eb9371; background-color: rgba(39, 41, 43, 0.83); box-shadow: 2px 2px 2px rgba(22, 9, 1, 0.6); border-radius: 2px; padding: 2px\\\">Software as a Service</span> hai yah ek distribution model hai jo ki internet mai software <span style=\"\">application</span>(jaise browser) ko ek service ke rup mai customer ko provide karta hai\",<br>        \"decoration\": {<br>            \"type\": \"number\",<br>            \"value\": 1<br>        }<br>    },<br>    {<br>        \"component\": \"text\",<br>        \"value\": \"SAAS ki sabse achhi bat yah hai ki hame kisi software <span style=\"\">application</span> ko install, maintain, tatha run karne ki jarurat nahi hoti hai kyuki eske sare software <span style=\"\">application</span> web browser se sidhe hi run ho jata hai\",<br>        \"decoration\": {<br>            \"type\": \"number\",<br>            \"value\": 2<br>        }<br>    },<br>    {<br>        \"component\": \"text\",<br>        \"value\": \"SAAS mai customer ka data puri tarh secure hota hai tatha agar system ko koe kharabi bhi aajaye tobhi data secure rahta hai.\",<br>        \"decoration\": {<br>            \"type\": \"number\",<br>            \"value\": 3<br>        }<br>    },<br>    {<br>        \"component\": \"text\",<br>        \"value\": \"SAAS <span style=\"\">application</span> jo hai vah SAAS provider ke server mai run hoti hai tatha SAAS <span style=\"\">application</span> ko kabhi kabhi hosted <span style=\"\">application</span> bhi karta hai\",<br>        \"decoration\": {<br>            \"type\": \"number\",<br>            \"value\": 4<br>        }<br>    },<br>    {<br>        \"component\": \"text\",<br>        \"value\": \"SAAS <span style=\"\">application</span> ke example google apps, office36 etc.<br><br>\",<br>        \"decoration\": {<br>            \"type\": \"number\",<br>            \"value\": 5<br>        }<br>    },<br>    {<br>        \"component\": \"header\",<br>        \"variant\": 2,<br>        \"value\": \"What is SAAS\"<br>    },<br>    {<br>        \"component\": \"<span style=\"\">youtube</span>\",<br>        \"value\": \"7fnuSIfFap0\"<br>    },<br>    {<br>        \"component\": \"<span style=\"\">youtube</span>\",<br>        \"value\": \"KUln2DXU5VE\"<br>    },<br>    {<br>        \"component\": \"header\",<br>        \"variant\": 2,<br>        \"value\": \"SAAS in E-commerce\"<br>    },<br>    {<br>        \"component\": \"<span style=\"\">youtube</span>\",<br>        \"value\": \"b2-5XaByaO4\"<br>    },<br>    {<br>        \"component\": \"header\",<br>        \"variant\": 3,<br>        \"value\": \"Ab aapko 30 mins ke liye aapas mei <span style=\\\"color: #eb9371; background-color: rgba(39, 41, 43, 0.83); box-shadow: 2px 2px 2px rgba(22, 9, 1, 0.6); border-radius: 2px; padding: 2px\\\">english</span> mei inn topics ke baarein mei baat karni hai.\"<br>    },<br>    {<br>        \"component\": \"text\",<br>        \"value\": \"Baat karte karte, aap observe karein, ki aap kitne tech words use kar paa rahe hai.\"<br>    },<br>    {<br>        \"component\": \"text\",<br>        \"value\": \"Aur agar aapka partner koi aisa tech word bolta hai, jo aapko nahi pata, ya aap generally use nahi kartein. Inn words ko bhi samajhne ki phir koshish karein.\"<br>    },<br>    {<br>        \"component\": \"text\",<br>        \"value\": \"Iss discussion ko karte hue, aap inn points ke baarein mei bhi soch sakte hai:\"<br>    },<br>    {<br>        \"component\": \"text\",<br>        \"value\": \"SAAS kya hai?\",<br>        \"decoration\": {<br>            \"type\": \"number\",<br>            \"value\": 1<br>        }<br>    },<br>    {<br>        \"component\": \"text\",<br>        \"value\": \"SAAS ke <span style=\"\">application</span> kay hai?\",<br>        \"decoration\": {<br>            \"type\": \"number\",<br>            \"value\": 2<br>        }<br>    },<br>    {<br>        \"component\": \"text\",<br>        \"value\": \"SAAS ke advantage discuss kare.\",<br>        \"decoration\": {<br>            \"type\": \"number\",<br>            \"value\": 3<br>        }<br>    },<br>    {<br>        \"component\": \"text\",<br>        \"value\": \"kya ham SAAS software ko Customize kar sakate hain?\",<br>        \"decoration\": {<br>            \"type\": \"number\",<br>            \"value\": 4<br>        }<br>    },<br>    {<br>        \"component\": \"text\",<br>        \"value\": \"Aapna data kon access karta hai SAAS mai?\",<br>        \"decoration\": {<br>            \"type\": \"number\",<br>            \"value\": 5<br>        }<br>    },<br>    {<br>        \"component\": \"text\",<br>        \"value\": \"SAAS mai aapna data safe hai kya?\",<br>        \"decoration\": {<br>            \"type\": \"number\",<br>            \"value\": 6<br>        }<br>    }<br>]"
	}
]