[
	{
		"component": "header",
		"variant": 1,
		"value": "Level Three"
	},
	{
		"component": "text",
		"value": "abroad",
		"decoration": {
			"type": "bullet"
		}
	},
	{
		"component": "text",
		"value": "absorb",
		"decoration": {
			"type": "bullet"
		}
	},
	{
		"component": "text",
		"value": "accept",
		"decoration": {
			"type": "bullet"
		}
	},
	{
		"component": "text",
		"value": "access",
		"decoration": {
			"type": "bullet"
		}
	},
	{
		"component": "text",
		"value": "accuse",
		"decoration": {
			"type": "bullet"
		}
	},
	{
		"component": "text",
		"value": "across",
		"decoration": {
			"type": "bullet"
		}
	},
	{
		"component": "text",
		"value": "action",
		"decoration": {
			"type": "bullet"
		}
	},
	{
		"component": "text",
		"value": "active",
		"decoration": {
			"type": "bullet"
		}
	},
	{
		"component": "text",
		"value": "actual",
		"decoration": {
			"type": "bullet"
		}
	},
	{
		"component": "text",
		"value": "adjust",
		"decoration": {
			"type": "bullet"
		}
	},
	{
		"component": "text",
		"value": "admire",
		"decoration": {
			"type": "bullet"
		}
	},
	{
		"component": "text",
		"value": "advice",
		"decoration": {
			"type": "bullet"
		}
	},
	{
		"component": "text",
		"value": "advise",
		"decoration": {
			"type": "bullet"
		}
	},
	{
		"component": "text",
		"value": "affair",
		"decoration": {
			"type": "bullet"
		}
	},
	{
		"component": "text",
		"value": "affect",
		"decoration": {
			"type": "bullet"
		}
	},
	{
		"component": "text",
		"value": "afford",
		"decoration": {
			"type": "bullet"
		}
	},
	{
		"component": "text",
		"value": "afraid",
		"decoration": {
			"type": "bullet"
		}
	},
	{
		"component": "text",
		"value": "agency",
		"decoration": {
			"type": "bullet"
		}
	},
	{
		"component": "text",
		"value": "agenda",
		"decoration": {
			"type": "bullet"
		}
	},
	{
		"component": "text",
		"value": "almost",
		"decoration": {
			"type": "bullet"
		}
	},
	{
		"component": "text",
		"value": "always",
		"decoration": {
			"type": "bullet"
		}
	},
	{
		"component": "text",
		"value": "amount",
		"decoration": {
			"type": "bullet"
		}
	},
	{
		"component": "text",
		"value": "annual",
		"decoration": {
			"type": "bullet"
		}
	},
	{
		"component": "text",
		"value": "answer",
		"decoration": {
			"type": "bullet"
		}
	},
	{
		"component": "text",
		"value": "anyone",
		"decoration": {
			"type": "bullet"
		}
	},
	{
		"component": "text",
		"value": "anyway",
		"decoration": {
			"type": "bullet"
		}
	},
	{
		"component": "text",
		"value": "appeal",
		"decoration": {
			"type": "bullet"
		}
	},
	{
		"component": "text",
		"value": "appear",
		"decoration": {
			"type": "bullet"
		}
	},
	{
		"component": "text",
		"value": "around",
		"decoration": {
			"type": "bullet"
		}
	},
	{
		"component": "text",
		"value": "arrest",
		"decoration": {
			"type": "bullet"
		}
	},
	{
		"component": "text",
		"value": "arrive",
		"decoration": {
			"type": "bullet"
		}
	},
	{
		"component": "text",
		"value": "artist",
		"decoration": {
			"type": "bullet"
		}
	},
	{
		"component": "text",
		"value": "asleep",
		"decoration": {
			"type": "bullet"
		}
	},
	{
		"component": "text",
		"value": "aspect",
		"decoration": {
			"type": "bullet"
		}
	},
	{
		"component": "text",
		"value": "assert",
		"decoration": {
			"type": "bullet"
		}
	},
	{
		"component": "text",
		"value": "assess",
		"decoration": {
			"type": "bullet"
		}
	},
	{
		"component": "text",
		"value": "assign",
		"decoration": {
			"type": "bullet"
		}
	},
	{
		"component": "text",
		"value": "assist",
		"decoration": {
			"type": "bullet"
		}
	},
	{
		"component": "text",
		"value": "assume",
		"decoration": {
			"type": "bullet"
		}
	},
	{
		"component": "text",
		"value": "assure",
		"decoration": {
			"type": "bullet"
		}
	},
	{
		"component": "text",
		"value": "attach",
		"decoration": {
			"type": "bullet"
		}
	},
	{
		"component": "text",
		"value": "attack",
		"decoration": {
			"type": "bullet"
		}
	},
	{
		"component": "text",
		"value": "attend",
		"decoration": {
			"type": "bullet"
		}
	},
	{
		"component": "text",
		"value": "author",
		"decoration": {
			"type": "bullet"
		}
	},
	{
		"component": "text",
		"value": "barely",
		"decoration": {
			"type": "bullet"
		}
	},
	{
		"component": "text",
		"value": "barrel",
		"decoration": {
			"type": "bullet"
		}
	},
	{
		"component": "text",
		"value": "basket",
		"decoration": {
			"type": "bullet"
		}
	},
	{
		"component": "text",
		"value": "battle",
		"decoration": {
			"type": "bullet"
		}
	},
	{
		"component": "text",
		"value": "beauty",
		"decoration": {
			"type": "bullet"
		}
	},
	{
		"component": "text",
		"value": "become",
		"decoration": {
			"type": "bullet"
		}
	},
	{
		"component": "text",
		"value": "before",
		"decoration": {
			"type": "bullet"
		}
	},
	{
		"component": "text",
		"value": "behind",
		"decoration": {
			"type": "bullet"
		}
	},
	{
		"component": "text",
		"value": "belief",
		"decoration": {
			"type": "bullet"
		}
	},
	{
		"component": "text",
		"value": "belong",
		"decoration": {
			"type": "bullet"
		}
	},
	{
		"component": "text",
		"value": "beside",
		"decoration": {
			"type": "bullet"
		}
	},
	{
		"component": "text",
		"value": "better",
		"decoration": {
			"type": "bullet"
		}
	},
	{
		"component": "text",
		"value": "beyond",
		"decoration": {
			"type": "bullet"
		}
	},
	{
		"component": "text",
		"value": "border",
		"decoration": {
			"type": "bullet"
		}
	},
	{
		"component": "text",
		"value": "borrow",
		"decoration": {
			"type": "bullet"
		}
	},
	{
		"component": "text",
		"value": "bother",
		"decoration": {
			"type": "bullet"
		}
	},
	{
		"component": "text",
		"value": "bottle",
		"decoration": {
			"type": "bullet"
		}
	},
	{
		"component": "text",
		"value": "bottom",
		"decoration": {
			"type": "bullet"
		}
	},
	{
		"component": "text",
		"value": "branch",
		"decoration": {
			"type": "bullet"
		}
	},
	{
		"component": "text",
		"value": "breast",
		"decoration": {
			"type": "bullet"
		}
	},
	{
		"component": "text",
		"value": "breath",
		"decoration": {
			"type": "bullet"
		}
	},
	{
		"component": "text",
		"value": "bridge",
		"decoration": {
			"type": "bullet"
		}
	},
	{
		"component": "text",
		"value": "bright",
		"decoration": {
			"type": "bullet"
		}
	},
	{
		"component": "text",
		"value": "broken",
		"decoration": {
			"type": "bullet"
		}
	},
	{
		"component": "text",
		"value": "budget",
		"decoration": {
			"type": "bullet"
		}
	},
	{
		"component": "text",
		"value": "bullet",
		"decoration": {
			"type": "bullet"
		}
	},
	{
		"component": "text",
		"value": "burden",
		"decoration": {
			"type": "bullet"
		}
	},
	{
		"component": "text",
		"value": "butter",
		"decoration": {
			"type": "bullet"
		}
	},
	{
		"component": "text",
		"value": "button",
		"decoration": {
			"type": "bullet"
		}
	},
	{
		"component": "text",
		"value": "camera",
		"decoration": {
			"type": "bullet"
		}
	},
	{
		"component": "text",
		"value": "campus",
		"decoration": {
			"type": "bullet"
		}
	},
	{
		"component": "text",
		"value": "cancer",
		"decoration": {
			"type": "bullet"
		}
	},
	{
		"component": "text",
		"value": "carbon",
		"decoration": {
			"type": "bullet"
		}
	},
	{
		"component": "text",
		"value": "career",
		"decoration": {
			"type": "bullet"
		}
	},
	{
		"component": "text",
		"value": "center",
		"decoration": {
			"type": "bullet"
		}
	},
	{
		"component": "text",
		"value": "chance",
		"decoration": {
			"type": "bullet"
		}
	},
	{
		"component": "text",
		"value": "change",
		"decoration": {
			"type": "bullet"
		}
	},
	{
		"component": "text",
		"value": "charge",
		"decoration": {
			"type": "bullet"
		}
	},
	{
		"component": "text",
		"value": "cheese",
		"decoration": {
			"type": "bullet"
		}
	},
	{
		"component": "text",
		"value": "choice",
		"decoration": {
			"type": "bullet"
		}
	},
	{
		"component": "text",
		"value": "choose",
		"decoration": {
			"type": "bullet"
		}
	},
	{
		"component": "text",
		"value": "church",
		"decoration": {
			"type": "bullet"
		}
	},
	{
		"component": "text",
		"value": "circle",
		"decoration": {
			"type": "bullet"
		}
	},
	{
		"component": "text",
		"value": "client",
		"decoration": {
			"type": "bullet"
		}
	},
	{
		"component": "text",
		"value": "clinic",
		"decoration": {
			"type": "bullet"
		}
	},
	{
		"component": "text",
		"value": "closer",
		"decoration": {
			"type": "bullet"
		}
	},
	{
		"component": "text",
		"value": "coffee",
		"decoration": {
			"type": "bullet"
		}
	},
	{
		"component": "text",
		"value": "column",
		"decoration": {
			"type": "bullet"
		}
	},
	{
		"component": "text",
		"value": "comedy",
		"decoration": {
			"type": "bullet"
		}
	},
	{
		"component": "text",
		"value": "commit",
		"decoration": {
			"type": "bullet"
		}
	},
	{
		"component": "text",
		"value": "common",
		"decoration": {
			"type": "bullet"
		}
	},
	{
		"component": "text",
		"value": "cookie",
		"decoration": {
			"type": "bullet"
		}
	},
	{
		"component": "text",
		"value": "corner",
		"decoration": {
			"type": "bullet"
		}
	},
	{
		"component": "text",
		"value": "cotton",
		"decoration": {
			"type": "bullet"
		}
	},
	{
		"component": "text",
		"value": "county",
		"decoration": {
			"type": "bullet"
		}
	},
	{
		"component": "text",
		"value": "couple",
		"decoration": {
			"type": "bullet"
		}
	},
	{
		"component": "text",
		"value": "course",
		"decoration": {
			"type": "bullet"
		}
	},
	{
		"component": "text",
		"value": "cousin",
		"decoration": {
			"type": "bullet"
		}
	},
	{
		"component": "text",
		"value": "create",
		"decoration": {
			"type": "bullet"
		}
	},
	{
		"component": "text",
		"value": "credit",
		"decoration": {
			"type": "bullet"
		}
	},
	{
		"component": "text",
		"value": "crisis",
		"decoration": {
			"type": "bullet"
		}
	},
	{
		"component": "text",
		"value": "critic",
		"decoration": {
			"type": "bullet"
		}
	},
	{
		"component": "text",
		"value": "custom",
		"decoration": {
			"type": "bullet"
		}
	},
	{
		"component": "text",
		"value": "damage",
		"decoration": {
			"type": "bullet"
		}
	},
	{
		"component": "text",
		"value": "danger",
		"decoration": {
			"type": "bullet"
		}
	},
	{
		"component": "text",
		"value": "dealer",
		"decoration": {
			"type": "bullet"
		}
	},
	{
		"component": "text",
		"value": "debate",
		"decoration": {
			"type": "bullet"
		}
	},
	{
		"component": "text",
		"value": "decade",
		"decoration": {
			"type": "bullet"
		}
	},
	{
		"component": "text",
		"value": "decide",
		"decoration": {
			"type": "bullet"
		}
	},
	{
		"component": "text",
		"value": "deeply",
		"decoration": {
			"type": "bullet"
		}
	},
	{
		"component": "text",
		"value": "defeat",
		"decoration": {
			"type": "bullet"
		}
	},
	{
		"component": "text",
		"value": "defend",
		"decoration": {
			"type": "bullet"
		}
	},
	{
		"component": "text",
		"value": "define",
		"decoration": {
			"type": "bullet"
		}
	},
	{
		"component": "text",
		"value": "degree",
		"decoration": {
			"type": "bullet"
		}
	},
	{
		"component": "text",
		"value": "demand",
		"decoration": {
			"type": "bullet"
		}
	},
	{
		"component": "text",
		"value": "depend",
		"decoration": {
			"type": "bullet"
		}
	},
	{
		"component": "text",
		"value": "depict",
		"decoration": {
			"type": "bullet"
		}
	},
	{
		"component": "text",
		"value": "deputy",
		"decoration": {
			"type": "bullet"
		}
	},
	{
		"component": "text",
		"value": "derive",
		"decoration": {
			"type": "bullet"
		}
	},
	{
		"component": "text",
		"value": "desert",
		"decoration": {
			"type": "bullet"
		}
	},
	{
		"component": "text",
		"value": "design",
		"decoration": {
			"type": "bullet"
		}
	},
	{
		"component": "text",
		"value": "desire",
		"decoration": {
			"type": "bullet"
		}
	},
	{
		"component": "text",
		"value": "detail",
		"decoration": {
			"type": "bullet"
		}
	},
	{
		"component": "text",
		"value": "detect",
		"decoration": {
			"type": "bullet"
		}
	},
	{
		"component": "text",
		"value": "device",
		"decoration": {
			"type": "bullet"
		}
	},
	{
		"component": "text",
		"value": "devote",
		"decoration": {
			"type": "bullet"
		}
	},
	{
		"component": "text",
		"value": "differ",
		"decoration": {
			"type": "bullet"
		}
	},
	{
		"component": "text",
		"value": "dining",
		"decoration": {
			"type": "bullet"
		}
	},
	{
		"component": "text",
		"value": "dinner",
		"decoration": {
			"type": "bullet"
		}
	},
	{
		"component": "text",
		"value": "direct",
		"decoration": {
			"type": "bullet"
		}
	},
	{
		"component": "text",
		"value": "divide",
		"decoration": {
			"type": "bullet"
		}
	},
	{
		"component": "text",
		"value": "doctor",
		"decoration": {
			"type": "bullet"
		}
	},
	{
		"component": "text",
		"value": "double",
		"decoration": {
			"type": "bullet"
		}
	},
	{
		"component": "text",
		"value": "driver",
		"decoration": {
			"type": "bullet"
		}
	},
	{
		"component": "text",
		"value": "during",
		"decoration": {
			"type": "bullet"
		}
	},
	{
		"component": "text",
		"value": "easily",
		"decoration": {
			"type": "bullet"
		}
	},
	{
		"component": "text",
		"value": "editor",
		"decoration": {
			"type": "bullet"
		}
	},
	{
		"component": "text",
		"value": "effect",
		"decoration": {
			"type": "bullet"
		}
	},
	{
		"component": "text",
		"value": "effort",
		"decoration": {
			"type": "bullet"
		}
	},
	{
		"component": "text",
		"value": "either",
		"decoration": {
			"type": "bullet"
		}
	},
	{
		"component": "text",
		"value": "e-mail",
		"decoration": {
			"type": "bullet"
		}
	},
	{
		"component": "text",
		"value": "emerge",
		"decoration": {
			"type": "bullet"
		}
	},
	{
		"component": "text",
		"value": "employ",
		"decoration": {
			"type": "bullet"
		}
	},
	{
		"component": "text",
		"value": "enable",
		"decoration": {
			"type": "bullet"
		}
	},
	{
		"component": "text",
		"value": "energy",
		"decoration": {
			"type": "bullet"
		}
	},
	{
		"component": "text",
		"value": "engage",
		"decoration": {
			"type": "bullet"
		}
	},
	{
		"component": "text",
		"value": "engine",
		"decoration": {
			"type": "bullet"
		}
	},
	{
		"component": "text",
		"value": "enough",
		"decoration": {
			"type": "bullet"
		}
	},
	{
		"component": "text",
		"value": "ensure",
		"decoration": {
			"type": "bullet"
		}
	},
	{
		"component": "text",
		"value": "entire",
		"decoration": {
			"type": "bullet"
		}
	},
	{
		"component": "text",
		"value": "escape",
		"decoration": {
			"type": "bullet"
		}
	},
	{
		"component": "text",
		"value": "estate",
		"decoration": {
			"type": "bullet"
		}
	},
	{
		"component": "text",
		"value": "ethics",
		"decoration": {
			"type": "bullet"
		}
	},
	{
		"component": "text",
		"value": "ethnic",
		"decoration": {
			"type": "bullet"
		}
	},
	{
		"component": "text",
		"value": "evolve",
		"decoration": {
			"type": "bullet"
		}
	},
	{
		"component": "text",
		"value": "exceed",
		"decoration": {
			"type": "bullet"
		}
	},
	{
		"component": "text",
		"value": "except",
		"decoration": {
			"type": "bullet"
		}
	},
	{
		"component": "text",
		"value": "expand",
		"decoration": {
			"type": "bullet"
		}
	},
	{
		"component": "text",
		"value": "expect",
		"decoration": {
			"type": "bullet"
		}
	},
	{
		"component": "text",
		"value": "expert",
		"decoration": {
			"type": "bullet"
		}
	},
	{
		"component": "text",
		"value": "expose",
		"decoration": {
			"type": "bullet"
		}
	},
	{
		"component": "text",
		"value": "extend",
		"decoration": {
			"type": "bullet"
		}
	},
	{
		"component": "text",
		"value": "extent",
		"decoration": {
			"type": "bullet"
		}
	},
	{
		"component": "text",
		"value": "fabric",
		"decoration": {
			"type": "bullet"
		}
	},
	{
		"component": "text",
		"value": "factor",
		"decoration": {
			"type": "bullet"
		}
	},
	{
		"component": "text",
		"value": "fairly",
		"decoration": {
			"type": "bullet"
		}
	},
	{
		"component": "text",
		"value": "family",
		"decoration": {
			"type": "bullet"
		}
	},
	{
		"component": "text",
		"value": "famous",
		"decoration": {
			"type": "bullet"
		}
	},
	{
		"component": "text",
		"value": "farmer",
		"decoration": {
			"type": "bullet"
		}
	},
	{
		"component": "text",
		"value": "father",
		"decoration": {
			"type": "bullet"
		}
	},
	{
		"component": "text",
		"value": "fellow",
		"decoration": {
			"type": "bullet"
		}
	},
	{
		"component": "text",
		"value": "female",
		"decoration": {
			"type": "bullet"
		}
	},
	{
		"component": "text",
		"value": "figure",
		"decoration": {
			"type": "bullet"
		}
	},
	{
		"component": "text",
		"value": "finger",
		"decoration": {
			"type": "bullet"
		}
	},
	{
		"component": "text",
		"value": "finish",
		"decoration": {
			"type": "bullet"
		}
	},
	{
		"component": "text",
		"value": "flavor",
		"decoration": {
			"type": "bullet"
		}
	},
	{
		"component": "text",
		"value": "flight",
		"decoration": {
			"type": "bullet"
		}
	},
	{
		"component": "text",
		"value": "flower",
		"decoration": {
			"type": "bullet"
		}
	},
	{
		"component": "text",
		"value": "follow",
		"decoration": {
			"type": "bullet"
		}
	},
	{
		"component": "text",
		"value": "forest",
		"decoration": {
			"type": "bullet"
		}
	},
	{
		"component": "text",
		"value": "forget",
		"decoration": {
			"type": "bullet"
		}
	},
	{
		"component": "text",
		"value": "formal",
		"decoration": {
			"type": "bullet"
		}
	},
	{
		"component": "text",
		"value": "former",
		"decoration": {
			"type": "bullet"
		}
	},
	{
		"component": "text",
		"value": "fourth",
		"decoration": {
			"type": "bullet"
		}
	},
	{
		"component": "text",
		"value": "freeze",
		"decoration": {
			"type": "bullet"
		}
	},
	{
		"component": "text",
		"value": "French",
		"decoration": {
			"type": "bullet"
		}
	},
	{
		"component": "text",
		"value": "friend",
		"decoration": {
			"type": "bullet"
		}
	},
	{
		"component": "text",
		"value": "future",
		"decoration": {
			"type": "bullet"
		}
	},
	{
		"component": "text",
		"value": "galaxy",
		"decoration": {
			"type": "bullet"
		}
	},
	{
		"component": "text",
		"value": "garage",
		"decoration": {
			"type": "bullet"
		}
	},
	{
		"component": "text",
		"value": "garden",
		"decoration": {
			"type": "bullet"
		}
	},
	{
		"component": "text",
		"value": "garlic",
		"decoration": {
			"type": "bullet"
		}
	},
	{
		"component": "text",
		"value": "gather",
		"decoration": {
			"type": "bullet"
		}
	},
	{
		"component": "text",
		"value": "gender",
		"decoration": {
			"type": "bullet"
		}
	},
	{
		"component": "text",
		"value": "gently",
		"decoration": {
			"type": "bullet"
		}
	},
	{
		"component": "text",
		"value": "German",
		"decoration": {
			"type": "bullet"
		}
	},
	{
		"component": "text",
		"value": "gifted",
		"decoration": {
			"type": "bullet"
		}
	},
	{
		"component": "text",
		"value": "glance",
		"decoration": {
			"type": "bullet"
		}
	},
	{
		"component": "text",
		"value": "global",
		"decoration": {
			"type": "bullet"
		}
	},
	{
		"component": "text",
		"value": "golden",
		"decoration": {
			"type": "bullet"
		}
	},
	{
		"component": "text",
		"value": "ground",
		"decoration": {
			"type": "bullet"
		}
	},
	{
		"component": "text",
		"value": "growth",
		"decoration": {
			"type": "bullet"
		}
	},
	{
		"component": "text",
		"value": "guilty",
		"decoration": {
			"type": "bullet"
		}
	},
	{
		"component": "text",
		"value": "handle",
		"decoration": {
			"type": "bullet"
		}
	},
	{
		"component": "text",
		"value": "happen",
		"decoration": {
			"type": "bullet"
		}
	},
	{
		"component": "text",
		"value": "hardly",
		"decoration": {
			"type": "bullet"
		}
	},
	{
		"component": "text",
		"value": "health",
		"decoration": {
			"type": "bullet"
		}
	},
	{
		"component": "text",
		"value": "heaven",
		"decoration": {
			"type": "bullet"
		}
	},
	{
		"component": "text",
		"value": "height",
		"decoration": {
			"type": "bullet"
		}
	},
	{
		"component": "text",
		"value": "highly",
		"decoration": {
			"type": "bullet"
		}
	},
	{
		"component": "text",
		"value": "honest",
		"decoration": {
			"type": "bullet"
		}
	},
	{
		"component": "text",
		"value": "horror",
		"decoration": {
			"type": "bullet"
		}
	},
	{
		"component": "text",
		"value": "hungry",
		"decoration": {
			"type": "bullet"
		}
	},
	{
		"component": "text",
		"value": "hunter",
		"decoration": {
			"type": "bullet"
		}
	},
	{
		"component": "text",
		"value": "ignore",
		"decoration": {
			"type": "bullet"
		}
	},
	{
		"component": "text",
		"value": "impact",
		"decoration": {
			"type": "bullet"
		}
	},
	{
		"component": "text",
		"value": "impose",
		"decoration": {
			"type": "bullet"
		}
	},
	{
		"component": "text",
		"value": "income",
		"decoration": {
			"type": "bullet"
		}
	},
	{
		"component": "text",
		"value": "indeed",
		"decoration": {
			"type": "bullet"
		}
	},
	{
		"component": "text",
		"value": "Indian",
		"decoration": {
			"type": "bullet"
		}
	},
	{
		"component": "text",
		"value": "infant",
		"decoration": {
			"type": "bullet"
		}
	},
	{
		"component": "text",
		"value": "inform",
		"decoration": {
			"type": "bullet"
		}
	},
	{
		"component": "text",
		"value": "injury",
		"decoration": {
			"type": "bullet"
		}
	},
	{
		"component": "text",
		"value": "inside",
		"decoration": {
			"type": "bullet"
		}
	},
	{
		"component": "text",
		"value": "insist",
		"decoration": {
			"type": "bullet"
		}
	},
	{
		"component": "text",
		"value": "intend",
		"decoration": {
			"type": "bullet"
		}
	},
	{
		"component": "text",
		"value": "invest",
		"decoration": {
			"type": "bullet"
		}
	},
	{
		"component": "text",
		"value": "invite",
		"decoration": {
			"type": "bullet"
		}
	},
	{
		"component": "text",
		"value": "island",
		"decoration": {
			"type": "bullet"
		}
	},
	{
		"component": "text",
		"value": "itself",
		"decoration": {
			"type": "bullet"
		}
	},
	{
		"component": "text",
		"value": "jacket",
		"decoration": {
			"type": "bullet"
		}
	},
	{
		"component": "text",
		"value": "Jewish",
		"decoration": {
			"type": "bullet"
		}
	},
	{
		"component": "text",
		"value": "junior",
		"decoration": {
			"type": "bullet"
		}
	},
	{
		"component": "text",
		"value": "killer",
		"decoration": {
			"type": "bullet"
		}
	},
	{
		"component": "text",
		"value": "latter",
		"decoration": {
			"type": "bullet"
		}
	},
	{
		"component": "text",
		"value": "launch",
		"decoration": {
			"type": "bullet"
		}
	},
	{
		"component": "text",
		"value": "lawyer",
		"decoration": {
			"type": "bullet"
		}
	},
	{
		"component": "text",
		"value": "leader",
		"decoration": {
			"type": "bullet"
		}
	},
	{
		"component": "text",
		"value": "league",
		"decoration": {
			"type": "bullet"
		}
	},
	{
		"component": "text",
		"value": "legacy",
		"decoration": {
			"type": "bullet"
		}
	},
	{
		"component": "text",
		"value": "legend",
		"decoration": {
			"type": "bullet"
		}
	},
	{
		"component": "text",
		"value": "length",
		"decoration": {
			"type": "bullet"
		}
	},
	{
		"component": "text",
		"value": "lesson",
		"decoration": {
			"type": "bullet"
		}
	},
	{
		"component": "text",
		"value": "letter",
		"decoration": {
			"type": "bullet"
		}
	},
	{
		"component": "text",
		"value": "likely",
		"decoration": {
			"type": "bullet"
		}
	},
	{
		"component": "text",
		"value": "listen",
		"decoration": {
			"type": "bullet"
		}
	},
	{
		"component": "text",
		"value": "little",
		"decoration": {
			"type": "bullet"
		}
	},
	{
		"component": "text",
		"value": "living",
		"decoration": {
			"type": "bullet"
		}
	},
	{
		"component": "text",
		"value": "locate",
		"decoration": {
			"type": "bullet"
		}
	},
	{
		"component": "text",
		"value": "lovely",
		"decoration": {
			"type": "bullet"
		}
	},
	{
		"component": "text",
		"value": "mainly",
		"decoration": {
			"type": "bullet"
		}
	},
	{
		"component": "text",
		"value": "makeup",
		"decoration": {
			"type": "bullet"
		}
	},
	{
		"component": "text",
		"value": "manage",
		"decoration": {
			"type": "bullet"
		}
	},
	{
		"component": "text",
		"value": "manner",
		"decoration": {
			"type": "bullet"
		}
	},
	{
		"component": "text",
		"value": "margin",
		"decoration": {
			"type": "bullet"
		}
	},
	{
		"component": "text",
		"value": "market",
		"decoration": {
			"type": "bullet"
		}
	},
	{
		"component": "text",
		"value": "master",
		"decoration": {
			"type": "bullet"
		}
	},
	{
		"component": "text",
		"value": "matter",
		"decoration": {
			"type": "bullet"
		}
	},
	{
		"component": "text",
		"value": "medium",
		"decoration": {
			"type": "bullet"
		}
	},
	{
		"component": "text",
		"value": "member",
		"decoration": {
			"type": "bullet"
		}
	},
	{
		"component": "text",
		"value": "memory",
		"decoration": {
			"type": "bullet"
		}
	},
	{
		"component": "text",
		"value": "mental",
		"decoration": {
			"type": "bullet"
		}
	},
	{
		"component": "text",
		"value": "merely",
		"decoration": {
			"type": "bullet"
		}
	},
	{
		"component": "text",
		"value": "method",
		"decoration": {
			"type": "bullet"
		}
	},
	{
		"component": "text",
		"value": "middle",
		"decoration": {
			"type": "bullet"
		}
	},
	{
		"component": "text",
		"value": "minute",
		"decoration": {
			"type": "bullet"
		}
	},
	{
		"component": "text",
		"value": "mirror",
		"decoration": {
			"type": "bullet"
		}
	},
	{
		"component": "text",
		"value": "mm-hmm",
		"decoration": {
			"type": "bullet"
		}
	},
	{
		"component": "text",
		"value": "modern",
		"decoration": {
			"type": "bullet"
		}
	},
	{
		"component": "text",
		"value": "modest",
		"decoration": {
			"type": "bullet"
		}
	},
	{
		"component": "text",
		"value": "moment",
		"decoration": {
			"type": "bullet"
		}
	},
	{
		"component": "text",
		"value": "mostly",
		"decoration": {
			"type": "bullet"
		}
	},
	{
		"component": "text",
		"value": "mother",
		"decoration": {
			"type": "bullet"
		}
	},
	{
		"component": "text",
		"value": "motion",
		"decoration": {
			"type": "bullet"
		}
	},
	{
		"component": "text",
		"value": "murder",
		"decoration": {
			"type": "bullet"
		}
	},
	{
		"component": "text",
		"value": "muscle",
		"decoration": {
			"type": "bullet"
		}
	},
	{
		"component": "text",
		"value": "museum",
		"decoration": {
			"type": "bullet"
		}
	},
	{
		"component": "text",
		"value": "Muslim",
		"decoration": {
			"type": "bullet"
		}
	},
	{
		"component": "text",
		"value": "mutual",
		"decoration": {
			"type": "bullet"
		}
	},
	{
		"component": "text",
		"value": "myself",
		"decoration": {
			"type": "bullet"
		}
	},
	{
		"component": "text",
		"value": "narrow",
		"decoration": {
			"type": "bullet"
		}
	},
	{
		"component": "text",
		"value": "nation",
		"decoration": {
			"type": "bullet"
		}
	},
	{
		"component": "text",
		"value": "native",
		"decoration": {
			"type": "bullet"
		}
	},
	{
		"component": "text",
		"value": "nature",
		"decoration": {
			"type": "bullet"
		}
	},
	{
		"component": "text",
		"value": "nearby",
		"decoration": {
			"type": "bullet"
		}
	},
	{
		"component": "text",
		"value": "nearly",
		"decoration": {
			"type": "bullet"
		}
	},
	{
		"component": "text",
		"value": "nobody",
		"decoration": {
			"type": "bullet"
		}
	},
	{
		"component": "text",
		"value": "normal",
		"decoration": {
			"type": "bullet"
		}
	},
	{
		"component": "text",
		"value": "notice",
		"decoration": {
			"type": "bullet"
		}
	},
	{
		"component": "text",
		"value": "notion",
		"decoration": {
			"type": "bullet"
		}
	},
	{
		"component": "text",
		"value": "number",
		"decoration": {
			"type": "bullet"
		}
	},
	{
		"component": "text",
		"value": "object",
		"decoration": {
			"type": "bullet"
		}
	},
	{
		"component": "text",
		"value": "obtain",
		"decoration": {
			"type": "bullet"
		}
	},
	{
		"component": "text",
		"value": "occupy",
		"decoration": {
			"type": "bullet"
		}
	},
	{
		"component": "text",
		"value": "office",
		"decoration": {
			"type": "bullet"
		}
	},
	{
		"component": "text",
		"value": "online",
		"decoration": {
			"type": "bullet"
		}
	},
	{
		"component": "text",
		"value": "oppose",
		"decoration": {
			"type": "bullet"
		}
	},
	{
		"component": "text",
		"value": "option",
		"decoration": {
			"type": "bullet"
		}
	},
	{
		"component": "text",
		"value": "orange",
		"decoration": {
			"type": "bullet"
		}
	},
	{
		"component": "text",
		"value": "origin",
		"decoration": {
			"type": "bullet"
		}
	},
	{
		"component": "text",
		"value": "others",
		"decoration": {
			"type": "bullet"
		}
	},
	{
		"component": "text",
		"value": "parent",
		"decoration": {
			"type": "bullet"
		}
	},
	{
		"component": "text",
		"value": "partly",
		"decoration": {
			"type": "bullet"
		}
	},
	{
		"component": "text",
		"value": "people",
		"decoration": {
			"type": "bullet"
		}
	},
	{
		"component": "text",
		"value": "pepper",
		"decoration": {
			"type": "bullet"
		}
	},
	{
		"component": "text",
		"value": "period",
		"decoration": {
			"type": "bullet"
		}
	},
	{
		"component": "text",
		"value": "permit",
		"decoration": {
			"type": "bullet"
		}
	},
	{
		"component": "text",
		"value": "person",
		"decoration": {
			"type": "bullet"
		}
	},
	{
		"component": "text",
		"value": "phrase",
		"decoration": {
			"type": "bullet"
		}
	},
	{
		"component": "text",
		"value": "planet",
		"decoration": {
			"type": "bullet"
		}
	},
	{
		"component": "text",
		"value": "player",
		"decoration": {
			"type": "bullet"
		}
	},
	{
		"component": "text",
		"value": "please",
		"decoration": {
			"type": "bullet"
		}
	},
	{
		"component": "text",
		"value": "plenty",
		"decoration": {
			"type": "bullet"
		}
	},
	{
		"component": "text",
		"value": "pocket",
		"decoration": {
			"type": "bullet"
		}
	},
	{
		"component": "text",
		"value": "poetry",
		"decoration": {
			"type": "bullet"
		}
	},
	{
		"component": "text",
		"value": "police",
		"decoration": {
			"type": "bullet"
		}
	},
	{
		"component": "text",
		"value": "policy",
		"decoration": {
			"type": "bullet"
		}
	},
	{
		"component": "text",
		"value": "potato",
		"decoration": {
			"type": "bullet"
		}
	},
	{
		"component": "text",
		"value": "powder",
		"decoration": {
			"type": "bullet"
		}
	},
	{
		"component": "text",
		"value": "prayer",
		"decoration": {
			"type": "bullet"
		}
	},
	{
		"component": "text",
		"value": "prefer",
		"decoration": {
			"type": "bullet"
		}
	},
	{
		"component": "text",
		"value": "pretty",
		"decoration": {
			"type": "bullet"
		}
	},
	{
		"component": "text",
		"value": "priest",
		"decoration": {
			"type": "bullet"
		}
	},
	{
		"component": "text",
		"value": "prison",
		"decoration": {
			"type": "bullet"
		}
	},
	{
		"component": "text",
		"value": "profit",
		"decoration": {
			"type": "bullet"
		}
	},
	{
		"component": "text",
		"value": "prompt",
		"decoration": {
			"type": "bullet"
		}
	},
	{
		"component": "text",
		"value": "proper",
		"decoration": {
			"type": "bullet"
		}
	},
	{
		"component": "text",
		"value": "public",
		"decoration": {
			"type": "bullet"
		}
	},
	{
		"component": "text",
		"value": "pursue",
		"decoration": {
			"type": "bullet"
		}
	},
	{
		"component": "text",
		"value": "racial",
		"decoration": {
			"type": "bullet"
		}
	},
	{
		"component": "text",
		"value": "rarely",
		"decoration": {
			"type": "bullet"
		}
	},
	{
		"component": "text",
		"value": "rather",
		"decoration": {
			"type": "bullet"
		}
	},
	{
		"component": "text",
		"value": "rating",
		"decoration": {
			"type": "bullet"
		}
	},
	{
		"component": "text",
		"value": "reader",
		"decoration": {
			"type": "bullet"
		}
	},
	{
		"component": "text",
		"value": "really",
		"decoration": {
			"type": "bullet"
		}
	},
	{
		"component": "text",
		"value": "reason",
		"decoration": {
			"type": "bullet"
		}
	},
	{
		"component": "text",
		"value": "recall",
		"decoration": {
			"type": "bullet"
		}
	},
	{
		"component": "text",
		"value": "recent",
		"decoration": {
			"type": "bullet"
		}
	},
	{
		"component": "text",
		"value": "recipe",
		"decoration": {
			"type": "bullet"
		}
	},
	{
		"component": "text",
		"value": "record",
		"decoration": {
			"type": "bullet"
		}
	},
	{
		"component": "text",
		"value": "reduce",
		"decoration": {
			"type": "bullet"
		}
	},
	{
		"component": "text",
		"value": "reform",
		"decoration": {
			"type": "bullet"
		}
	},
	{
		"component": "text",
		"value": "refuse",
		"decoration": {
			"type": "bullet"
		}
	},
	{
		"component": "text",
		"value": "regard",
		"decoration": {
			"type": "bullet"
		}
	},
	{
		"component": "text",
		"value": "regime",
		"decoration": {
			"type": "bullet"
		}
	},
	{
		"component": "text",
		"value": "region",
		"decoration": {
			"type": "bullet"
		}
	},
	{
		"component": "text",
		"value": "reject",
		"decoration": {
			"type": "bullet"
		}
	},
	{
		"component": "text",
		"value": "relate",
		"decoration": {
			"type": "bullet"
		}
	},
	{
		"component": "text",
		"value": "relief",
		"decoration": {
			"type": "bullet"
		}
	},
	{
		"component": "text",
		"value": "remain",
		"decoration": {
			"type": "bullet"
		}
	},
	{
		"component": "text",
		"value": "remind",
		"decoration": {
			"type": "bullet"
		}
	},
	{
		"component": "text",
		"value": "remote",
		"decoration": {
			"type": "bullet"
		}
	},
	{
		"component": "text",
		"value": "remove",
		"decoration": {
			"type": "bullet"
		}
	},
	{
		"component": "text",
		"value": "repeat",
		"decoration": {
			"type": "bullet"
		}
	},
	{
		"component": "text",
		"value": "report",
		"decoration": {
			"type": "bullet"
		}
	},
	{
		"component": "text",
		"value": "resist",
		"decoration": {
			"type": "bullet"
		}
	},
	{
		"component": "text",
		"value": "resort",
		"decoration": {
			"type": "bullet"
		}
	},
	{
		"component": "text",
		"value": "result",
		"decoration": {
			"type": "bullet"
		}
	},
	{
		"component": "text",
		"value": "retain",
		"decoration": {
			"type": "bullet"
		}
	},
	{
		"component": "text",
		"value": "retire",
		"decoration": {
			"type": "bullet"
		}
	},
	{
		"component": "text",
		"value": "return",
		"decoration": {
			"type": "bullet"
		}
	},
	{
		"component": "text",
		"value": "reveal",
		"decoration": {
			"type": "bullet"
		}
	},
	{
		"component": "text",
		"value": "review",
		"decoration": {
			"type": "bullet"
		}
	},
	{
		"component": "text",
		"value": "rhythm",
		"decoration": {
			"type": "bullet"
		}
	},
	{
		"component": "text",
		"value": "sacred",
		"decoration": {
			"type": "bullet"
		}
	},
	{
		"component": "text",
		"value": "safety",
		"decoration": {
			"type": "bullet"
		}
	},
	{
		"component": "text",
		"value": "salary",
		"decoration": {
			"type": "bullet"
		}
	},
	{
		"component": "text",
		"value": "sample",
		"decoration": {
			"type": "bullet"
		}
	},
	{
		"component": "text",
		"value": "saving",
		"decoration": {
			"type": "bullet"
		}
	},
	{
		"component": "text",
		"value": "scared",
		"decoration": {
			"type": "bullet"
		}
	},
	{
		"component": "text",
		"value": "scheme",
		"decoration": {
			"type": "bullet"
		}
	},
	{
		"component": "text",
		"value": "school",
		"decoration": {
			"type": "bullet"
		}
	},
	{
		"component": "text",
		"value": "scream",
		"decoration": {
			"type": "bullet"
		}
	},
	{
		"component": "text",
		"value": "screen",
		"decoration": {
			"type": "bullet"
		}
	},
	{
		"component": "text",
		"value": "script",
		"decoration": {
			"type": "bullet"
		}
	},
	{
		"component": "text",
		"value": "search",
		"decoration": {
			"type": "bullet"
		}
	},
	{
		"component": "text",
		"value": "season",
		"decoration": {
			"type": "bullet"
		}
	},
	{
		"component": "text",
		"value": "second",
		"decoration": {
			"type": "bullet"
		}
	},
	{
		"component": "text",
		"value": "secret",
		"decoration": {
			"type": "bullet"
		}
	},
	{
		"component": "text",
		"value": "sector",
		"decoration": {
			"type": "bullet"
		}
	},
	{
		"component": "text",
		"value": "secure",
		"decoration": {
			"type": "bullet"
		}
	},
	{
		"component": "text",
		"value": "select",
		"decoration": {
			"type": "bullet"
		}
	},
	{
		"component": "text",
		"value": "Senate",
		"decoration": {
			"type": "bullet"
		}
	},
	{
		"component": "text",
		"value": "senior",
		"decoration": {
			"type": "bullet"
		}
	},
	{
		"component": "text",
		"value": "series",
		"decoration": {
			"type": "bullet"
		}
	},
	{
		"component": "text",
		"value": "settle",
		"decoration": {
			"type": "bullet"
		}
	},
	{
		"component": "text",
		"value": "severe",
		"decoration": {
			"type": "bullet"
		}
	},
	{
		"component": "text",
		"value": "sexual",
		"decoration": {
			"type": "bullet"
		}
	},
	{
		"component": "text",
		"value": "shadow",
		"decoration": {
			"type": "bullet"
		}
	},
	{
		"component": "text",
		"value": "should",
		"decoration": {
			"type": "bullet"
		}
	},
	{
		"component": "text",
		"value": "shower",
		"decoration": {
			"type": "bullet"
		}
	},
	{
		"component": "text",
		"value": "signal",
		"decoration": {
			"type": "bullet"
		}
	},
	{
		"component": "text",
		"value": "silent",
		"decoration": {
			"type": "bullet"
		}
	},
	{
		"component": "text",
		"value": "silver",
		"decoration": {
			"type": "bullet"
		}
	},
	{
		"component": "text",
		"value": "simple",
		"decoration": {
			"type": "bullet"
		}
	},
	{
		"component": "text",
		"value": "simply",
		"decoration": {
			"type": "bullet"
		}
	},
	{
		"component": "text",
		"value": "singer",
		"decoration": {
			"type": "bullet"
		}
	},
	{
		"component": "text",
		"value": "single",
		"decoration": {
			"type": "bullet"
		}
	},
	{
		"component": "text",
		"value": "sister",
		"decoration": {
			"type": "bullet"
		}
	},
	{
		"component": "text",
		"value": "slight",
		"decoration": {
			"type": "bullet"
		}
	},
	{
		"component": "text",
		"value": "slowly",
		"decoration": {
			"type": "bullet"
		}
	},
	{
		"component": "text",
		"value": "smooth",
		"decoration": {
			"type": "bullet"
		}
	},
	{
		"component": "text",
		"value": "soccer",
		"decoration": {
			"type": "bullet"
		}
	},
	{
		"component": "text",
		"value": "social",
		"decoration": {
			"type": "bullet"
		}
	},
	{
		"component": "text",
		"value": "source",
		"decoration": {
			"type": "bullet"
		}
	},
	{
		"component": "text",
		"value": "Soviet",
		"decoration": {
			"type": "bullet"
		}
	},
	{
		"component": "text",
		"value": "speech",
		"decoration": {
			"type": "bullet"
		}
	},
	{
		"component": "text",
		"value": "spirit",
		"decoration": {
			"type": "bullet"
		}
	},
	{
		"component": "text",
		"value": "spread",
		"decoration": {
			"type": "bullet"
		}
	},
	{
		"component": "text",
		"value": "spring",
		"decoration": {
			"type": "bullet"
		}
	},
	{
		"component": "text",
		"value": "square",
		"decoration": {
			"type": "bullet"
		}
	},
	{
		"component": "text",
		"value": "stable",
		"decoration": {
			"type": "bullet"
		}
	},
	{
		"component": "text",
		"value": "status",
		"decoration": {
			"type": "bullet"
		}
	},
	{
		"component": "text",
		"value": "steady",
		"decoration": {
			"type": "bullet"
		}
	},
	{
		"component": "text",
		"value": "stream",
		"decoration": {
			"type": "bullet"
		}
	},
	{
		"component": "text",
		"value": "street",
		"decoration": {
			"type": "bullet"
		}
	},
	{
		"component": "text",
		"value": "stress",
		"decoration": {
			"type": "bullet"
		}
	},
	{
		"component": "text",
		"value": "strike",
		"decoration": {
			"type": "bullet"
		}
	},
	{
		"component": "text",
		"value": "string",
		"decoration": {
			"type": "bullet"
		}
	},
	{
		"component": "text",
		"value": "stroke",
		"decoration": {
			"type": "bullet"
		}
	},
	{
		"component": "text",
		"value": "strong",
		"decoration": {
			"type": "bullet"
		}
	},
	{
		"component": "text",
		"value": "studio",
		"decoration": {
			"type": "bullet"
		}
	},
	{
		"component": "text",
		"value": "stupid",
		"decoration": {
			"type": "bullet"
		}
	},
	{
		"component": "text",
		"value": "submit",
		"decoration": {
			"type": "bullet"
		}
	},
	{
		"component": "text",
		"value": "sudden",
		"decoration": {
			"type": "bullet"
		}
	},
	{
		"component": "text",
		"value": "suffer",
		"decoration": {
			"type": "bullet"
		}
	},
	{
		"component": "text",
		"value": "summer",
		"decoration": {
			"type": "bullet"
		}
	},
	{
		"component": "text",
		"value": "summit",
		"decoration": {
			"type": "bullet"
		}
	},
	{
		"component": "text",
		"value": "supply",
		"decoration": {
			"type": "bullet"
		}
	},
	{
		"component": "text",
		"value": "surely",
		"decoration": {
			"type": "bullet"
		}
	},
	{
		"component": "text",
		"value": "survey",
		"decoration": {
			"type": "bullet"
		}
	},
	{
		"component": "text",
		"value": "switch",
		"decoration": {
			"type": "bullet"
		}
	},
	{
		"component": "text",
		"value": "symbol",
		"decoration": {
			"type": "bullet"
		}
	},
	{
		"component": "text",
		"value": "system",
		"decoration": {
			"type": "bullet"
		}
	},
	{
		"component": "text",
		"value": "tactic",
		"decoration": {
			"type": "bullet"
		}
	},
	{
		"component": "text",
		"value": "talent",
		"decoration": {
			"type": "bullet"
		}
	},
	{
		"component": "text",
		"value": "target",
		"decoration": {
			"type": "bullet"
		}
	},
	{
		"component": "text",
		"value": "tennis",
		"decoration": {
			"type": "bullet"
		}
	},
	{
		"component": "text",
		"value": "terror",
		"decoration": {
			"type": "bullet"
		}
	},
	{
		"component": "text",
		"value": "thanks",
		"decoration": {
			"type": "bullet"
		}
	},
	{
		"component": "text",
		"value": "theory",
		"decoration": {
			"type": "bullet"
		}
	},
	{
		"component": "text",
		"value": "thirty",
		"decoration": {
			"type": "bullet"
		}
	},
	{
		"component": "text",
		"value": "though",
		"decoration": {
			"type": "bullet"
		}
	},
	{
		"component": "text",
		"value": "threat",
		"decoration": {
			"type": "bullet"
		}
	},
	{
		"component": "text",
		"value": "throat",
		"decoration": {
			"type": "bullet"
		}
	},
	{
		"component": "text",
		"value": "ticket",
		"decoration": {
			"type": "bullet"
		}
	},
	{
		"component": "text",
		"value": "tissue",
		"decoration": {
			"type": "bullet"
		}
	},
	{
		"component": "text",
		"value": "tomato",
		"decoration": {
			"type": "bullet"
		}
	},
	{
		"component": "text",
		"value": "tongue",
		"decoration": {
			"type": "bullet"
		}
	},
	{
		"component": "text",
		"value": "toward",
		"decoration": {
			"type": "bullet"
		}
	},
	{
		"component": "text",
		"value": "travel",
		"decoration": {
			"type": "bullet"
		}
	},
	{
		"component": "text",
		"value": "treaty",
		"decoration": {
			"type": "bullet"
		}
	},
	{
		"component": "text",
		"value": "tunnel",
		"decoration": {
			"type": "bullet"
		}
	},
	{
		"component": "text",
		"value": "twelve",
		"decoration": {
			"type": "bullet"
		}
	},
	{
		"component": "text",
		"value": "twenty",
		"decoration": {
			"type": "bullet"
		}
	},
	{
		"component": "text",
		"value": "unable",
		"decoration": {
			"type": "bullet"
		}
	},
	{
		"component": "text",
		"value": "unique",
		"decoration": {
			"type": "bullet"
		}
	},
	{
		"component": "text",
		"value": "United",
		"decoration": {
			"type": "bullet"
		}
	},
	{
		"component": "text",
		"value": "unless",
		"decoration": {
			"type": "bullet"
		}
	},
	{
		"component": "text",
		"value": "unlike",
		"decoration": {
			"type": "bullet"
		}
	},
	{
		"component": "text",
		"value": "useful",
		"decoration": {
			"type": "bullet"
		}
	},
	{
		"component": "text",
		"value": "valley",
		"decoration": {
			"type": "bullet"
		}
	},
	{
		"component": "text",
		"value": "versus",
		"decoration": {
			"type": "bullet"
		}
	},
	{
		"component": "text",
		"value": "vessel",
		"decoration": {
			"type": "bullet"
		}
	},
	{
		"component": "text",
		"value": "victim",
		"decoration": {
			"type": "bullet"
		}
	},
	{
		"component": "text",
		"value": "viewer",
		"decoration": {
			"type": "bullet"
		}
	},
	{
		"component": "text",
		"value": "virtue",
		"decoration": {
			"type": "bullet"
		}
	},
	{
		"component": "text",
		"value": "vision",
		"decoration": {
			"type": "bullet"
		}
	},
	{
		"component": "text",
		"value": "visual",
		"decoration": {
			"type": "bullet"
		}
	},
	{
		"component": "text",
		"value": "volume",
		"decoration": {
			"type": "bullet"
		}
	},
	{
		"component": "text",
		"value": "wander",
		"decoration": {
			"type": "bullet"
		}
	},
	{
		"component": "text",
		"value": "wealth",
		"decoration": {
			"type": "bullet"
		}
	},
	{
		"component": "text",
		"value": "weapon",
		"decoration": {
			"type": "bullet"
		}
	},
	{
		"component": "text",
		"value": "weekly",
		"decoration": {
			"type": "bullet"
		}
	},
	{
		"component": "text",
		"value": "weight",
		"decoration": {
			"type": "bullet"
		}
	},
	{
		"component": "text",
		"value": "widely",
		"decoration": {
			"type": "bullet"
		}
	},
	{
		"component": "text",
		"value": "window",
		"decoration": {
			"type": "bullet"
		}
	},
	{
		"component": "text",
		"value": "winner",
		"decoration": {
			"type": "bullet"
		}
	},
	{
		"component": "text",
		"value": "winter",
		"decoration": {
			"type": "bullet"
		}
	},
	{
		"component": "text",
		"value": "wisdom",
		"decoration": {
			"type": "bullet"
		}
	},
	{
		"component": "text",
		"value": "within",
		"decoration": {
			"type": "bullet"
		}
	},
	{
		"component": "text",
		"value": "wonder",
		"decoration": {
			"type": "bullet"
		}
	},
	{
		"component": "text",
		"value": "wooden",
		"decoration": {
			"type": "bullet"
		}
	},
	{
		"component": "text",
		"value": "worker",
		"decoration": {
			"type": "bullet"
		}
	},
	{
		"component": "text",
		"value": "writer",
		"decoration": {
			"type": "bullet"
		}
	},
	{
		"component": "text",
		"value": "yellow",
		"decoration": {
			"type": "bullet"
		}
	},
	{
		"component": "text",
		"value": "abandon",
		"decoration": {
			"type": "bullet"
		}
	},
	{
		"component": "text",
		"value": "ability",
		"decoration": {
			"type": "bullet"
		}
	},
	{
		"component": "text",
		"value": "absence",
		"decoration": {
			"type": "bullet"
		}
	},
	{
		"component": "text",
		"value": "account",
		"decoration": {
			"type": "bullet"
		}
	},
	{
		"component": "text",
		"value": "achieve",
		"decoration": {
			"type": "bullet"
		}
	},
	{
		"component": "text",
		"value": "acquire",
		"decoration": {
			"type": "bullet"
		}
	},
	{
		"component": "text",
		"value": "actress",
		"decoration": {
			"type": "bullet"
		}
	},
	{
		"component": "text",
		"value": "address",
		"decoration": {
			"type": "bullet"
		}
	},
	{
		"component": "text",
		"value": "advance",
		"decoration": {
			"type": "bullet"
		}
	},
	{
		"component": "text",
		"value": "adviser",
		"decoration": {
			"type": "bullet"
		}
	},
	{
		"component": "text",
		"value": "African",
		"decoration": {
			"type": "bullet"
		}
	},
	{
		"component": "text",
		"value": "against",
		"decoration": {
			"type": "bullet"
		}
	},
	{
		"component": "text",
		"value": "airline",
		"decoration": {
			"type": "bullet"
		}
	},
	{
		"component": "text",
		"value": "airport",
		"decoration": {
			"type": "bullet"
		}
	},
	{
		"component": "text",
		"value": "alcohol",
		"decoration": {
			"type": "bullet"
		}
	},
	{
		"component": "text",
		"value": "already",
		"decoration": {
			"type": "bullet"
		}
	},
	{
		"component": "text",
		"value": "amazing",
		"decoration": {
			"type": "bullet"
		}
	},
	{
		"component": "text",
		"value": "analyst",
		"decoration": {
			"type": "bullet"
		}
	},
	{
		"component": "text",
		"value": "analyze",
		"decoration": {
			"type": "bullet"
		}
	},
	{
		"component": "text",
		"value": "ancient",
		"decoration": {
			"type": "bullet"
		}
	},
	{
		"component": "text",
		"value": "another",
		"decoration": {
			"type": "bullet"
		}
	},
	{
		"component": "text",
		"value": "anxiety",
		"decoration": {
			"type": "bullet"
		}
	},
	{
		"component": "text",
		"value": "anybody",
		"decoration": {
			"type": "bullet"
		}
	},
	{
		"component": "text",
		"value": "anymore",
		"decoration": {
			"type": "bullet"
		}
	},
	{
		"component": "text",
		"value": "appoint",
		"decoration": {
			"type": "bullet"
		}
	},
	{
		"component": "text",
		"value": "approve",
		"decoration": {
			"type": "bullet"
		}
	},
	{
		"component": "text",
		"value": "arrange",
		"decoration": {
			"type": "bullet"
		}
	},
	{
		"component": "text",
		"value": "arrival",
		"decoration": {
			"type": "bullet"
		}
	},
	{
		"component": "text",
		"value": "article",
		"decoration": {
			"type": "bullet"
		}
	},
	{
		"component": "text",
		"value": "assault",
		"decoration": {
			"type": "bullet"
		}
	},
	{
		"component": "text",
		"value": "athlete",
		"decoration": {
			"type": "bullet"
		}
	},
	{
		"component": "text",
		"value": "attempt",
		"decoration": {
			"type": "bullet"
		}
	},
	{
		"component": "text",
		"value": "attract",
		"decoration": {
			"type": "bullet"
		}
	},
	{
		"component": "text",
		"value": "average",
		"decoration": {
			"type": "bullet"
		}
	},
	{
		"component": "text",
		"value": "balance",
		"decoration": {
			"type": "bullet"
		}
	},
	{
		"component": "text",
		"value": "barrier",
		"decoration": {
			"type": "bullet"
		}
	},
	{
		"component": "text",
		"value": "battery",
		"decoration": {
			"type": "bullet"
		}
	},
	{
		"component": "text",
		"value": "because",
		"decoration": {
			"type": "bullet"
		}
	},
	{
		"component": "text",
		"value": "bedroom",
		"decoration": {
			"type": "bullet"
		}
	},
	{
		"component": "text",
		"value": "believe",
		"decoration": {
			"type": "bullet"
		}
	},
	{
		"component": "text",
		"value": "beneath",
		"decoration": {
			"type": "bullet"
		}
	},
	{
		"component": "text",
		"value": "benefit",
		"decoration": {
			"type": "bullet"
		}
	},
	{
		"component": "text",
		"value": "besides",
		"decoration": {
			"type": "bullet"
		}
	},
	{
		"component": "text",
		"value": "between",
		"decoration": {
			"type": "bullet"
		}
	},
	{
		"component": "text",
		"value": "billion",
		"decoration": {
			"type": "bullet"
		}
	},
	{
		"component": "text",
		"value": "blanket",
		"decoration": {
			"type": "bullet"
		}
	},
	{
		"component": "text",
		"value": "bombing",
		"decoration": {
			"type": "bullet"
		}
	},
	{
		"component": "text",
		"value": "breathe",
		"decoration": {
			"type": "bullet"
		}
	},
	{
		"component": "text",
		"value": "briefly",
		"decoration": {
			"type": "bullet"
		}
	},
	{
		"component": "text",
		"value": "British",
		"decoration": {
			"type": "bullet"
		}
	},
	{
		"component": "text",
		"value": "brother",
		"decoration": {
			"type": "bullet"
		}
	},
	{
		"component": "text",
		"value": "cabinet",
		"decoration": {
			"type": "bullet"
		}
	},
	{
		"component": "text",
		"value": "capable",
		"decoration": {
			"type": "bullet"
		}
	},
	{
		"component": "text",
		"value": "capital",
		"decoration": {
			"type": "bullet"
		}
	},
	{
		"component": "text",
		"value": "captain",
		"decoration": {
			"type": "bullet"
		}
	},
	{
		"component": "text",
		"value": "capture",
		"decoration": {
			"type": "bullet"
		}
	},
	{
		"component": "text",
		"value": "careful",
		"decoration": {
			"type": "bullet"
		}
	},
	{
		"component": "text",
		"value": "carrier",
		"decoration": {
			"type": "bullet"
		}
	},
	{
		"component": "text",
		"value": "ceiling",
		"decoration": {
			"type": "bullet"
		}
	},
	{
		"component": "text",
		"value": "central",
		"decoration": {
			"type": "bullet"
		}
	},
	{
		"component": "text",
		"value": "century",
		"decoration": {
			"type": "bullet"
		}
	},
	{
		"component": "text",
		"value": "certain",
		"decoration": {
			"type": "bullet"
		}
	},
	{
		"component": "text",
		"value": "chamber",
		"decoration": {
			"type": "bullet"
		}
	},
	{
		"component": "text",
		"value": "channel",
		"decoration": {
			"type": "bullet"
		}
	},
	{
		"component": "text",
		"value": "chapter",
		"decoration": {
			"type": "bullet"
		}
	},
	{
		"component": "text",
		"value": "charity",
		"decoration": {
			"type": "bullet"
		}
	},
	{
		"component": "text",
		"value": "chicken",
		"decoration": {
			"type": "bullet"
		}
	},
	{
		"component": "text",
		"value": "Chinese",
		"decoration": {
			"type": "bullet"
		}
	},
	{
		"component": "text",
		"value": "citizen",
		"decoration": {
			"type": "bullet"
		}
	},
	{
		"component": "text",
		"value": "classic",
		"decoration": {
			"type": "bullet"
		}
	},
	{
		"component": "text",
		"value": "clearly",
		"decoration": {
			"type": "bullet"
		}
	},
	{
		"component": "text",
		"value": "climate",
		"decoration": {
			"type": "bullet"
		}
	},
	{
		"component": "text",
		"value": "closely",
		"decoration": {
			"type": "bullet"
		}
	},
	{
		"component": "text",
		"value": "clothes",
		"decoration": {
			"type": "bullet"
		}
	},
	{
		"component": "text",
		"value": "cluster",
		"decoration": {
			"type": "bullet"
		}
	},
	{
		"component": "text",
		"value": "collect",
		"decoration": {
			"type": "bullet"
		}
	},
	{
		"component": "text",
		"value": "college",
		"decoration": {
			"type": "bullet"
		}
	},
	{
		"component": "text",
		"value": "combine",
		"decoration": {
			"type": "bullet"
		}
	},
	{
		"component": "text",
		"value": "comfort",
		"decoration": {
			"type": "bullet"
		}
	},
	{
		"component": "text",
		"value": "command",
		"decoration": {
			"type": "bullet"
		}
	},
	{
		"component": "text",
		"value": "comment",
		"decoration": {
			"type": "bullet"
		}
	},
	{
		"component": "text",
		"value": "company",
		"decoration": {
			"type": "bullet"
		}
	},
	{
		"component": "text",
		"value": "compare",
		"decoration": {
			"type": "bullet"
		}
	},
	{
		"component": "text",
		"value": "compete",
		"decoration": {
			"type": "bullet"
		}
	},
	{
		"component": "text",
		"value": "complex",
		"decoration": {
			"type": "bullet"
		}
	},
	{
		"component": "text",
		"value": "compose",
		"decoration": {
			"type": "bullet"
		}
	},
	{
		"component": "text",
		"value": "concept",
		"decoration": {
			"type": "bullet"
		}
	},
	{
		"component": "text",
		"value": "concern",
		"decoration": {
			"type": "bullet"
		}
	},
	{
		"component": "text",
		"value": "concert",
		"decoration": {
			"type": "bullet"
		}
	},
	{
		"component": "text",
		"value": "conduct",
		"decoration": {
			"type": "bullet"
		}
	},
	{
		"component": "text",
		"value": "confirm",
		"decoration": {
			"type": "bullet"
		}
	},
	{
		"component": "text",
		"value": "connect",
		"decoration": {
			"type": "bullet"
		}
	},
	{
		"component": "text",
		"value": "consist",
		"decoration": {
			"type": "bullet"
		}
	},
	{
		"component": "text",
		"value": "consume",
		"decoration": {
			"type": "bullet"
		}
	},
	{
		"component": "text",
		"value": "contact",
		"decoration": {
			"type": "bullet"
		}
	},
	{
		"component": "text",
		"value": "contain",
		"decoration": {
			"type": "bullet"
		}
	},
	{
		"component": "text",
		"value": "content",
		"decoration": {
			"type": "bullet"
		}
	},
	{
		"component": "text",
		"value": "contest",
		"decoration": {
			"type": "bullet"
		}
	},
	{
		"component": "text",
		"value": "context",
		"decoration": {
			"type": "bullet"
		}
	},
	{
		"component": "text",
		"value": "control",
		"decoration": {
			"type": "bullet"
		}
	},
	{
		"component": "text",
		"value": "convert",
		"decoration": {
			"type": "bullet"
		}
	},
	{
		"component": "text",
		"value": "cooking",
		"decoration": {
			"type": "bullet"
		}
	},
	{
		"component": "text",
		"value": "correct",
		"decoration": {
			"type": "bullet"
		}
	},
	{
		"component": "text",
		"value": "council",
		"decoration": {
			"type": "bullet"
		}
	},
	{
		"component": "text",
		"value": "counter",
		"decoration": {
			"type": "bullet"
		}
	},
	{
		"component": "text",
		"value": "country",
		"decoration": {
			"type": "bullet"
		}
	},
	{
		"component": "text",
		"value": "courage",
		"decoration": {
			"type": "bullet"
		}
	},
	{
		"component": "text",
		"value": "crucial",
		"decoration": {
			"type": "bullet"
		}
	},
	{
		"component": "text",
		"value": "culture",
		"decoration": {
			"type": "bullet"
		}
	},
	{
		"component": "text",
		"value": "curious",
		"decoration": {
			"type": "bullet"
		}
	},
	{
		"component": "text",
		"value": "current",
		"decoration": {
			"type": "bullet"
		}
	},
	{
		"component": "text",
		"value": "declare",
		"decoration": {
			"type": "bullet"
		}
	},
	{
		"component": "text",
		"value": "decline",
		"decoration": {
			"type": "bullet"
		}
	},
	{
		"component": "text",
		"value": "defense",
		"decoration": {
			"type": "bullet"
		}
	},
	{
		"component": "text",
		"value": "deficit",
		"decoration": {
			"type": "bullet"
		}
	},
	{
		"component": "text",
		"value": "deliver",
		"decoration": {
			"type": "bullet"
		}
	},
	{
		"component": "text",
		"value": "deserve",
		"decoration": {
			"type": "bullet"
		}
	},
	{
		"component": "text",
		"value": "despite",
		"decoration": {
			"type": "bullet"
		}
	},
	{
		"component": "text",
		"value": "destroy",
		"decoration": {
			"type": "bullet"
		}
	},
	{
		"component": "text",
		"value": "develop",
		"decoration": {
			"type": "bullet"
		}
	},
	{
		"component": "text",
		"value": "digital",
		"decoration": {
			"type": "bullet"
		}
	},
	{
		"component": "text",
		"value": "discuss",
		"decoration": {
			"type": "bullet"
		}
	},
	{
		"component": "text",
		"value": "disease",
		"decoration": {
			"type": "bullet"
		}
	},
	{
		"component": "text",
		"value": "dismiss",
		"decoration": {
			"type": "bullet"
		}
	},
	{
		"component": "text",
		"value": "display",
		"decoration": {
			"type": "bullet"
		}
	},
	{
		"component": "text",
		"value": "dispute",
		"decoration": {
			"type": "bullet"
		}
	},
	{
		"component": "text",
		"value": "distant",
		"decoration": {
			"type": "bullet"
		}
	},
	{
		"component": "text",
		"value": "diverse",
		"decoration": {
			"type": "bullet"
		}
	},
	{
		"component": "text",
		"value": "divorce",
		"decoration": {
			"type": "bullet"
		}
	},
	{
		"component": "text",
		"value": "drawing",
		"decoration": {
			"type": "bullet"
		}
	},
	{
		"component": "text",
		"value": "eastern",
		"decoration": {
			"type": "bullet"
		}
	},
	{
		"component": "text",
		"value": "economy",
		"decoration": {
			"type": "bullet"
		}
	},
	{
		"component": "text",
		"value": "edition",
		"decoration": {
			"type": "bullet"
		}
	},
	{
		"component": "text",
		"value": "educate",
		"decoration": {
			"type": "bullet"
		}
	},
	{
		"component": "text",
		"value": "elderly",
		"decoration": {
			"type": "bullet"
		}
	},
	{
		"component": "text",
		"value": "element",
		"decoration": {
			"type": "bullet"
		}
	},
	{
		"component": "text",
		"value": "embrace",
		"decoration": {
			"type": "bullet"
		}
	},
	{
		"component": "text",
		"value": "emotion",
		"decoration": {
			"type": "bullet"
		}
	},
	{
		"component": "text",
		"value": "English",
		"decoration": {
			"type": "bullet"
		}
	},
	{
		"component": "text",
		"value": "enhance",
		"decoration": {
			"type": "bullet"
		}
	},
	{
		"component": "text",
		"value": "episode",
		"decoration": {
			"type": "bullet"
		}
	},
	{
		"component": "text",
		"value": "equally",
		"decoration": {
			"type": "bullet"
		}
	},
	{
		"component": "text",
		"value": "evening",
		"decoration": {
			"type": "bullet"
		}
	},
	{
		"component": "text",
		"value": "exactly",
		"decoration": {
			"type": "bullet"
		}
	},
	{
		"component": "text",
		"value": "examine",
		"decoration": {
			"type": "bullet"
		}
	},
	{
		"component": "text",
		"value": "example",
		"decoration": {
			"type": "bullet"
		}
	},
	{
		"component": "text",
		"value": "exhibit",
		"decoration": {
			"type": "bullet"
		}
	},
	{
		"component": "text",
		"value": "expense",
		"decoration": {
			"type": "bullet"
		}
	},
	{
		"component": "text",
		"value": "explain",
		"decoration": {
			"type": "bullet"
		}
	},
	{
		"component": "text",
		"value": "explode",
		"decoration": {
			"type": "bullet"
		}
	},
	{
		"component": "text",
		"value": "explore",
		"decoration": {
			"type": "bullet"
		}
	},
	{
		"component": "text",
		"value": "express",
		"decoration": {
			"type": "bullet"
		}
	},
	{
		"component": "text",
		"value": "extreme",
		"decoration": {
			"type": "bullet"
		}
	},
	{
		"component": "text",
		"value": "factory",
		"decoration": {
			"type": "bullet"
		}
	},
	{
		"component": "text",
		"value": "faculty",
		"decoration": {
			"type": "bullet"
		}
	},
	{
		"component": "text",
		"value": "failure",
		"decoration": {
			"type": "bullet"
		}
	},
	{
		"component": "text",
		"value": "fantasy",
		"decoration": {
			"type": "bullet"
		}
	},
	{
		"component": "text",
		"value": "fashion",
		"decoration": {
			"type": "bullet"
		}
	},
	{
		"component": "text",
		"value": "feature",
		"decoration": {
			"type": "bullet"
		}
	},
	{
		"component": "text",
		"value": "federal",
		"decoration": {
			"type": "bullet"
		}
	},
	{
		"component": "text",
		"value": "feeling",
		"decoration": {
			"type": "bullet"
		}
	},
	{
		"component": "text",
		"value": "fiction",
		"decoration": {
			"type": "bullet"
		}
	},
	{
		"component": "text",
		"value": "fifteen",
		"decoration": {
			"type": "bullet"
		}
	},
	{
		"component": "text",
		"value": "fighter",
		"decoration": {
			"type": "bullet"
		}
	},
	{
		"component": "text",
		"value": "finally",
		"decoration": {
			"type": "bullet"
		}
	},
	{
		"component": "text",
		"value": "finance",
		"decoration": {
			"type": "bullet"
		}
	},
	{
		"component": "text",
		"value": "finding",
		"decoration": {
			"type": "bullet"
		}
	},
	{
		"component": "text",
		"value": "fishing",
		"decoration": {
			"type": "bullet"
		}
	},
	{
		"component": "text",
		"value": "fitness",
		"decoration": {
			"type": "bullet"
		}
	},
	{
		"component": "text",
		"value": "foreign",
		"decoration": {
			"type": "bullet"
		}
	},
	{
		"component": "text",
		"value": "forever",
		"decoration": {
			"type": "bullet"
		}
	},
	{
		"component": "text",
		"value": "formula",
		"decoration": {
			"type": "bullet"
		}
	},
	{
		"component": "text",
		"value": "fortune",
		"decoration": {
			"type": "bullet"
		}
	},
	{
		"component": "text",
		"value": "forward",
		"decoration": {
			"type": "bullet"
		}
	},
	{
		"component": "text",
		"value": "founder",
		"decoration": {
			"type": "bullet"
		}
	},
	{
		"component": "text",
		"value": "freedom",
		"decoration": {
			"type": "bullet"
		}
	},
	{
		"component": "text",
		"value": "funding",
		"decoration": {
			"type": "bullet"
		}
	},
	{
		"component": "text",
		"value": "funeral",
		"decoration": {
			"type": "bullet"
		}
	},
	{
		"component": "text",
		"value": "gallery",
		"decoration": {
			"type": "bullet"
		}
	},
	{
		"component": "text",
		"value": "general",
		"decoration": {
			"type": "bullet"
		}
	},
	{
		"component": "text",
		"value": "genetic",
		"decoration": {
			"type": "bullet"
		}
	},
	{
		"component": "text",
		"value": "gesture",
		"decoration": {
			"type": "bullet"
		}
	},
	{
		"component": "text",
		"value": "grocery",
		"decoration": {
			"type": "bullet"
		}
	},
	{
		"component": "text",
		"value": "growing",
		"decoration": {
			"type": "bullet"
		}
	},
	{
		"component": "text",
		"value": "habitat",
		"decoration": {
			"type": "bullet"
		}
	},
	{
		"component": "text",
		"value": "handful",
		"decoration": {
			"type": "bullet"
		}
	},
	{
		"component": "text",
		"value": "healthy",
		"decoration": {
			"type": "bullet"
		}
	},
	{
		"component": "text",
		"value": "hearing",
		"decoration": {
			"type": "bullet"
		}
	},
	{
		"component": "text",
		"value": "heavily",
		"decoration": {
			"type": "bullet"
		}
	},
	{
		"component": "text",
		"value": "helpful",
		"decoration": {
			"type": "bullet"
		}
	},
	{
		"component": "text",
		"value": "herself",
		"decoration": {
			"type": "bullet"
		}
	},
	{
		"component": "text",
		"value": "highway",
		"decoration": {
			"type": "bullet"
		}
	},
	{
		"component": "text",
		"value": "himself",
		"decoration": {
			"type": "bullet"
		}
	},
	{
		"component": "text",
		"value": "history",
		"decoration": {
			"type": "bullet"
		}
	},
	{
		"component": "text",
		"value": "holiday",
		"decoration": {
			"type": "bullet"
		}
	},
	{
		"component": "text",
		"value": "horizon",
		"decoration": {
			"type": "bullet"
		}
	},
	{
		"component": "text",
		"value": "housing",
		"decoration": {
			"type": "bullet"
		}
	},
	{
		"component": "text",
		"value": "however",
		"decoration": {
			"type": "bullet"
		}
	},
	{
		"component": "text",
		"value": "hundred",
		"decoration": {
			"type": "bullet"
		}
	},
	{
		"component": "text",
		"value": "hunting",
		"decoration": {
			"type": "bullet"
		}
	},
	{
		"component": "text",
		"value": "husband",
		"decoration": {
			"type": "bullet"
		}
	},
	{
		"component": "text",
		"value": "illegal",
		"decoration": {
			"type": "bullet"
		}
	},
	{
		"component": "text",
		"value": "illness",
		"decoration": {
			"type": "bullet"
		}
	},
	{
		"component": "text",
		"value": "imagine",
		"decoration": {
			"type": "bullet"
		}
	},
	{
		"component": "text",
		"value": "impress",
		"decoration": {
			"type": "bullet"
		}
	},
	{
		"component": "text",
		"value": "improve",
		"decoration": {
			"type": "bullet"
		}
	},
	{
		"component": "text",
		"value": "include",
		"decoration": {
			"type": "bullet"
		}
	},
	{
		"component": "text",
		"value": "initial",
		"decoration": {
			"type": "bullet"
		}
	},
	{
		"component": "text",
		"value": "inquiry",
		"decoration": {
			"type": "bullet"
		}
	},
	{
		"component": "text",
		"value": "insight",
		"decoration": {
			"type": "bullet"
		}
	},
	{
		"component": "text",
		"value": "inspire",
		"decoration": {
			"type": "bullet"
		}
	},
	{
		"component": "text",
		"value": "install",
		"decoration": {
			"type": "bullet"
		}
	},
	{
		"component": "text",
		"value": "instead",
		"decoration": {
			"type": "bullet"
		}
	},
	{
		"component": "text",
		"value": "intense",
		"decoration": {
			"type": "bullet"
		}
	},
	{
		"component": "text",
		"value": "involve",
		"decoration": {
			"type": "bullet"
		}
	},
	{
		"component": "text",
		"value": "Islamic",
		"decoration": {
			"type": "bullet"
		}
	},
	{
		"component": "text",
		"value": "Israeli",
		"decoration": {
			"type": "bullet"
		}
	},
	{
		"component": "text",
		"value": "Italian",
		"decoration": {
			"type": "bullet"
		}
	},
	{
		"component": "text",
		"value": "journal",
		"decoration": {
			"type": "bullet"
		}
	},
	{
		"component": "text",
		"value": "journey",
		"decoration": {
			"type": "bullet"
		}
	},
	{
		"component": "text",
		"value": "justice",
		"decoration": {
			"type": "bullet"
		}
	},
	{
		"component": "text",
		"value": "justify",
		"decoration": {
			"type": "bullet"
		}
	},
	{
		"component": "text",
		"value": "killing",
		"decoration": {
			"type": "bullet"
		}
	},
	{
		"component": "text",
		"value": "kitchen",
		"decoration": {
			"type": "bullet"
		}
	},
	{
		"component": "text",
		"value": "largely",
		"decoration": {
			"type": "bullet"
		}
	},
	{
		"component": "text",
		"value": "lawsuit",
		"decoration": {
			"type": "bullet"
		}
	},
	{
		"component": "text",
		"value": "leading",
		"decoration": {
			"type": "bullet"
		}
	},
	{
		"component": "text",
		"value": "leather",
		"decoration": {
			"type": "bullet"
		}
	},
	{
		"component": "text",
		"value": "liberal",
		"decoration": {
			"type": "bullet"
		}
	},
	{
		"component": "text",
		"value": "library",
		"decoration": {
			"type": "bullet"
		}
	},
	{
		"component": "text",
		"value": "license",
		"decoration": {
			"type": "bullet"
		}
	},
	{
		"component": "text",
		"value": "limited",
		"decoration": {
			"type": "bullet"
		}
	},
	{
		"component": "text",
		"value": "machine",
		"decoration": {
			"type": "bullet"
		}
	},
	{
		"component": "text",
		"value": "manager",
		"decoration": {
			"type": "bullet"
		}
	},
	{
		"component": "text",
		"value": "married",
		"decoration": {
			"type": "bullet"
		}
	},
	{
		"component": "text",
		"value": "massive",
		"decoration": {
			"type": "bullet"
		}
	},
	{
		"component": "text",
		"value": "meaning",
		"decoration": {
			"type": "bullet"
		}
	},
	{
		"component": "text",
		"value": "measure",
		"decoration": {
			"type": "bullet"
		}
	},
	{
		"component": "text",
		"value": "medical",
		"decoration": {
			"type": "bullet"
		}
	},
	{
		"component": "text",
		"value": "meeting",
		"decoration": {
			"type": "bullet"
		}
	},
	{
		"component": "text",
		"value": "mention",
		"decoration": {
			"type": "bullet"
		}
	},
	{
		"component": "text",
		"value": "message",
		"decoration": {
			"type": "bullet"
		}
	},
	{
		"component": "text",
		"value": "Mexican",
		"decoration": {
			"type": "bullet"
		}
	},
	{
		"component": "text",
		"value": "million",
		"decoration": {
			"type": "bullet"
		}
	},
	{
		"component": "text",
		"value": "miracle",
		"decoration": {
			"type": "bullet"
		}
	},
	{
		"component": "text",
		"value": "missile",
		"decoration": {
			"type": "bullet"
		}
	},
	{
		"component": "text",
		"value": "mission",
		"decoration": {
			"type": "bullet"
		}
	},
	{
		"component": "text",
		"value": "mistake",
		"decoration": {
			"type": "bullet"
		}
	},
	{
		"component": "text",
		"value": "mixture",
		"decoration": {
			"type": "bullet"
		}
	},
	{
		"component": "text",
		"value": "monitor",
		"decoration": {
			"type": "bullet"
		}
	},
	{
		"component": "text",
		"value": "morning",
		"decoration": {
			"type": "bullet"
		}
	},
	{
		"component": "text",
		"value": "musical",
		"decoration": {
			"type": "bullet"
		}
	},
	{
		"component": "text",
		"value": "mystery",
		"decoration": {
			"type": "bullet"
		}
	},
	{
		"component": "text",
		"value": "natural",
		"decoration": {
			"type": "bullet"
		}
	},
	{
		"component": "text",
		"value": "neither",
		"decoration": {
			"type": "bullet"
		}
	},
	{
		"component": "text",
		"value": "nervous",
		"decoration": {
			"type": "bullet"
		}
	},
	{
		"component": "text",
		"value": "network",
		"decoration": {
			"type": "bullet"
		}
	},
	{
		"component": "text",
		"value": "nothing",
		"decoration": {
			"type": "bullet"
		}
	},
	{
		"component": "text",
		"value": "nowhere",
		"decoration": {
			"type": "bullet"
		}
	},
	{
		"component": "text",
		"value": "nuclear",
		"decoration": {
			"type": "bullet"
		}
	},
	{
		"component": "text",
		"value": "observe",
		"decoration": {
			"type": "bullet"
		}
	},
	{
		"component": "text",
		"value": "obvious",
		"decoration": {
			"type": "bullet"
		}
	},
	{
		"component": "text",
		"value": "offense",
		"decoration": {
			"type": "bullet"
		}
	},
	{
		"component": "text",
		"value": "officer",
		"decoration": {
			"type": "bullet"
		}
	},
	{
		"component": "text",
		"value": "Olympic",
		"decoration": {
			"type": "bullet"
		}
	},
	{
		"component": "text",
		"value": "ongoing",
		"decoration": {
			"type": "bullet"
		}
	},
	{
		"component": "text",
		"value": "opening",
		"decoration": {
			"type": "bullet"
		}
	},
	{
		"component": "text",
		"value": "operate",
		"decoration": {
			"type": "bullet"
		}
	},
	{
		"component": "text",
		"value": "opinion",
		"decoration": {
			"type": "bullet"
		}
	},
	{
		"component": "text",
		"value": "organic",
		"decoration": {
			"type": "bullet"
		}
	},
	{
		"component": "text",
		"value": "outcome",
		"decoration": {
			"type": "bullet"
		}
	},
	{
		"component": "text",
		"value": "outside",
		"decoration": {
			"type": "bullet"
		}
	},
	{
		"component": "text",
		"value": "overall",
		"decoration": {
			"type": "bullet"
		}
	},
	{
		"component": "text",
		"value": "package",
		"decoration": {
			"type": "bullet"
		}
	},
	{
		"component": "text",
		"value": "painful",
		"decoration": {
			"type": "bullet"
		}
	},
	{
		"component": "text",
		"value": "painter",
		"decoration": {
			"type": "bullet"
		}
	},
	{
		"component": "text",
		"value": "parking",
		"decoration": {
			"type": "bullet"
		}
	},
	{
		"component": "text",
		"value": "partner",
		"decoration": {
			"type": "bullet"
		}
	},
	{
		"component": "text",
		"value": "passage",
		"decoration": {
			"type": "bullet"
		}
	},
	{
		"component": "text",
		"value": "passion",
		"decoration": {
			"type": "bullet"
		}
	},
	{
		"component": "text",
		"value": "patient",
		"decoration": {
			"type": "bullet"
		}
	},
	{
		"component": "text",
		"value": "pattern",
		"decoration": {
			"type": "bullet"
		}
	},
	{
		"component": "text",
		"value": "payment",
		"decoration": {
			"type": "bullet"
		}
	},
	{
		"component": "text",
		"value": "penalty",
		"decoration": {
			"type": "bullet"
		}
	},
	{
		"component": "text",
		"value": "perfect",
		"decoration": {
			"type": "bullet"
		}
	},
	{
		"component": "text",
		"value": "perform",
		"decoration": {
			"type": "bullet"
		}
	},
	{
		"component": "text",
		"value": "perhaps",
		"decoration": {
			"type": "bullet"
		}
	},
	{
		"component": "text",
		"value": "picture",
		"decoration": {
			"type": "bullet"
		}
	},
	{
		"component": "text",
		"value": "plastic",
		"decoration": {
			"type": "bullet"
		}
	},
	{
		"component": "text",
		"value": "popular",
		"decoration": {
			"type": "bullet"
		}
	},
	{
		"component": "text",
		"value": "portion",
		"decoration": {
			"type": "bullet"
		}
	},
	{
		"component": "text",
		"value": "portray",
		"decoration": {
			"type": "bullet"
		}
	},
	{
		"component": "text",
		"value": "possess",
		"decoration": {
			"type": "bullet"
		}
	},
	{
		"component": "text",
		"value": "poverty",
		"decoration": {
			"type": "bullet"
		}
	},
	{
		"component": "text",
		"value": "predict",
		"decoration": {
			"type": "bullet"
		}
	},
	{
		"component": "text",
		"value": "prepare",
		"decoration": {
			"type": "bullet"
		}
	},
	{
		"component": "text",
		"value": "present",
		"decoration": {
			"type": "bullet"
		}
	},
	{
		"component": "text",
		"value": "pretend",
		"decoration": {
			"type": "bullet"
		}
	},
	{
		"component": "text",
		"value": "prevent",
		"decoration": {
			"type": "bullet"
		}
	},
	{
		"component": "text",
		"value": "primary",
		"decoration": {
			"type": "bullet"
		}
	},
	{
		"component": "text",
		"value": "privacy",
		"decoration": {
			"type": "bullet"
		}
	},
	{
		"component": "text",
		"value": "private",
		"decoration": {
			"type": "bullet"
		}
	},
	{
		"component": "text",
		"value": "problem",
		"decoration": {
			"type": "bullet"
		}
	},
	{
		"component": "text",
		"value": "proceed",
		"decoration": {
			"type": "bullet"
		}
	},
	{
		"component": "text",
		"value": "process",
		"decoration": {
			"type": "bullet"
		}
	},
	{
		"component": "text",
		"value": "produce",
		"decoration": {
			"type": "bullet"
		}
	},
	{
		"component": "text",
		"value": "product",
		"decoration": {
			"type": "bullet"
		}
	},
	{
		"component": "text",
		"value": "profile",
		"decoration": {
			"type": "bullet"
		}
	},
	{
		"component": "text",
		"value": "program",
		"decoration": {
			"type": "bullet"
		}
	},
	{
		"component": "text",
		"value": "project",
		"decoration": {
			"type": "bullet"
		}
	},
	{
		"component": "text",
		"value": "promise",
		"decoration": {
			"type": "bullet"
		}
	},
	{
		"component": "text",
		"value": "promote",
		"decoration": {
			"type": "bullet"
		}
	},
	{
		"component": "text",
		"value": "propose",
		"decoration": {
			"type": "bullet"
		}
	},
	{
		"component": "text",
		"value": "protect",
		"decoration": {
			"type": "bullet"
		}
	},
	{
		"component": "text",
		"value": "protein",
		"decoration": {
			"type": "bullet"
		}
	},
	{
		"component": "text",
		"value": "protest",
		"decoration": {
			"type": "bullet"
		}
	},
	{
		"component": "text",
		"value": "provide",
		"decoration": {
			"type": "bullet"
		}
	},
	{
		"component": "text",
		"value": "publish",
		"decoration": {
			"type": "bullet"
		}
	},
	{
		"component": "text",
		"value": "purpose",
		"decoration": {
			"type": "bullet"
		}
	},
	{
		"component": "text",
		"value": "qualify",
		"decoration": {
			"type": "bullet"
		}
	},
	{
		"component": "text",
		"value": "quality",
		"decoration": {
			"type": "bullet"
		}
	},
	{
		"component": "text",
		"value": "quarter",
		"decoration": {
			"type": "bullet"
		}
	},
	{
		"component": "text",
		"value": "quickly",
		"decoration": {
			"type": "bullet"
		}
	},
	{
		"component": "text",
		"value": "quietly",
		"decoration": {
			"type": "bullet"
		}
	},
	{
		"component": "text",
		"value": "radical",
		"decoration": {
			"type": "bullet"
		}
	},
	{
		"component": "text",
		"value": "rapidly",
		"decoration": {
			"type": "bullet"
		}
	},
	{
		"component": "text",
		"value": "reading",
		"decoration": {
			"type": "bullet"
		}
	},
	{
		"component": "text",
		"value": "reality",
		"decoration": {
			"type": "bullet"
		}
	},
	{
		"component": "text",
		"value": "realize",
		"decoration": {
			"type": "bullet"
		}
	},
	{
		"component": "text",
		"value": "receive",
		"decoration": {
			"type": "bullet"
		}
	},
	{
		"component": "text",
		"value": "recover",
		"decoration": {
			"type": "bullet"
		}
	},
	{
		"component": "text",
		"value": "recruit",
		"decoration": {
			"type": "bullet"
		}
	},
	{
		"component": "text",
		"value": "reflect",
		"decoration": {
			"type": "bullet"
		}
	},
	{
		"component": "text",
		"value": "refugee",
		"decoration": {
			"type": "bullet"
		}
	},
	{
		"component": "text",
		"value": "regular",
		"decoration": {
			"type": "bullet"
		}
	},
	{
		"component": "text",
		"value": "release",
		"decoration": {
			"type": "bullet"
		}
	},
	{
		"component": "text",
		"value": "replace",
		"decoration": {
			"type": "bullet"
		}
	},
	{
		"component": "text",
		"value": "request",
		"decoration": {
			"type": "bullet"
		}
	},
	{
		"component": "text",
		"value": "require",
		"decoration": {
			"type": "bullet"
		}
	},
	{
		"component": "text",
		"value": "resolve",
		"decoration": {
			"type": "bullet"
		}
	},
	{
		"component": "text",
		"value": "respect",
		"decoration": {
			"type": "bullet"
		}
	},
	{
		"component": "text",
		"value": "respond",
		"decoration": {
			"type": "bullet"
		}
	},
	{
		"component": "text",
		"value": "restore",
		"decoration": {
			"type": "bullet"
		}
	},
	{
		"component": "text",
		"value": "revenue",
		"decoration": {
			"type": "bullet"
		}
	},
	{
		"component": "text",
		"value": "roughly",
		"decoration": {
			"type": "bullet"
		}
	},
	{
		"component": "text",
		"value": "routine",
		"decoration": {
			"type": "bullet"
		}
	},
	{
		"component": "text",
		"value": "running",
		"decoration": {
			"type": "bullet"
		}
	},
	{
		"component": "text",
		"value": "Russian",
		"decoration": {
			"type": "bullet"
		}
	},
	{
		"component": "text",
		"value": "satisfy",
		"decoration": {
			"type": "bullet"
		}
	},
	{
		"component": "text",
		"value": "scandal",
		"decoration": {
			"type": "bullet"
		}
	},
	{
		"component": "text",
		"value": "scholar",
		"decoration": {
			"type": "bullet"
		}
	},
	{
		"component": "text",
		"value": "science",
		"decoration": {
			"type": "bullet"
		}
	},
	{
		"component": "text",
		"value": "section",
		"decoration": {
			"type": "bullet"
		}
	},
	{
		"component": "text",
		"value": "segment",
		"decoration": {
			"type": "bullet"
		}
	},
	{
		"component": "text",
		"value": "senator",
		"decoration": {
			"type": "bullet"
		}
	},
	{
		"component": "text",
		"value": "serious",
		"decoration": {
			"type": "bullet"
		}
	},
	{
		"component": "text",
		"value": "service",
		"decoration": {
			"type": "bullet"
		}
	},
	{
		"component": "text",
		"value": "session",
		"decoration": {
			"type": "bullet"
		}
	},
	{
		"component": "text",
		"value": "setting",
		"decoration": {
			"type": "bullet"
		}
	},
	{
		"component": "text",
		"value": "several",
		"decoration": {
			"type": "bullet"
		}
	},
	{
		"component": "text",
		"value": "shelter",
		"decoration": {
			"type": "bullet"
		}
	},
	{
		"component": "text",
		"value": "shortly",
		"decoration": {
			"type": "bullet"
		}
	},
	{
		"component": "text",
		"value": "silence",
		"decoration": {
			"type": "bullet"
		}
	},
	{
		"component": "text",
		"value": "similar",
		"decoration": {
			"type": "bullet"
		}
	},
	{
		"component": "text",
		"value": "society",
		"decoration": {
			"type": "bullet"
		}
	},
	{
		"component": "text",
		"value": "soldier",
		"decoration": {
			"type": "bullet"
		}
	},
	{
		"component": "text",
		"value": "somehow",
		"decoration": {
			"type": "bullet"
		}
	},
	{
		"component": "text",
		"value": "someone",
		"decoration": {
			"type": "bullet"
		}
	},
	{
		"component": "text",
		"value": "Spanish",
		"decoration": {
			"type": "bullet"
		}
	},
	{
		"component": "text",
		"value": "speaker",
		"decoration": {
			"type": "bullet"
		}
	},
	{
		"component": "text",
		"value": "special",
		"decoration": {
			"type": "bullet"
		}
	},
	{
		"component": "text",
		"value": "species",
		"decoration": {
			"type": "bullet"
		}
	},
	{
		"component": "text",
		"value": "squeeze",
		"decoration": {
			"type": "bullet"
		}
	},
	{
		"component": "text",
		"value": "station",
		"decoration": {
			"type": "bullet"
		}
	},
	{
		"component": "text",
		"value": "stomach",
		"decoration": {
			"type": "bullet"
		}
	},
	{
		"component": "text",
		"value": "storage",
		"decoration": {
			"type": "bullet"
		}
	},
	{
		"component": "text",
		"value": "strange",
		"decoration": {
			"type": "bullet"
		}
	},
	{
		"component": "text",
		"value": "stretch",
		"decoration": {
			"type": "bullet"
		}
	},
	{
		"component": "text",
		"value": "student",
		"decoration": {
			"type": "bullet"
		}
	},
	{
		"component": "text",
		"value": "subject",
		"decoration": {
			"type": "bullet"
		}
	},
	{
		"component": "text",
		"value": "succeed",
		"decoration": {
			"type": "bullet"
		}
	},
	{
		"component": "text",
		"value": "success",
		"decoration": {
			"type": "bullet"
		}
	},
	{
		"component": "text",
		"value": "suggest",
		"decoration": {
			"type": "bullet"
		}
	},
	{
		"component": "text",
		"value": "suicide",
		"decoration": {
			"type": "bullet"
		}
	},
	{
		"component": "text",
		"value": "support",
		"decoration": {
			"type": "bullet"
		}
	},
	{
		"component": "text",
		"value": "suppose",
		"decoration": {
			"type": "bullet"
		}
	},
	{
		"component": "text",
		"value": "Supreme",
		"decoration": {
			"type": "bullet"
		}
	},
	{
		"component": "text",
		"value": "surface",
		"decoration": {
			"type": "bullet"
		}
	},
	{
		"component": "text",
		"value": "surgery",
		"decoration": {
			"type": "bullet"
		}
	},
	{
		"component": "text",
		"value": "survive",
		"decoration": {
			"type": "bullet"
		}
	},
	{
		"component": "text",
		"value": "suspect",
		"decoration": {
			"type": "bullet"
		}
	},
	{
		"component": "text",
		"value": "sustain",
		"decoration": {
			"type": "bullet"
		}
	},
	{
		"component": "text",
		"value": "symptom",
		"decoration": {
			"type": "bullet"
		}
	},
	{
		"component": "text",
		"value": "teacher",
		"decoration": {
			"type": "bullet"
		}
	},
	{
		"component": "text",
		"value": "tension",
		"decoration": {
			"type": "bullet"
		}
	},
	{
		"component": "text",
		"value": "testify",
		"decoration": {
			"type": "bullet"
		}
	},
	{
		"component": "text",
		"value": "testing",
		"decoration": {
			"type": "bullet"
		}
	},
	{
		"component": "text",
		"value": "theater",
		"decoration": {
			"type": "bullet"
		}
	},
	{
		"component": "text",
		"value": "therapy",
		"decoration": {
			"type": "bullet"
		}
	},
	{
		"component": "text",
		"value": "thought",
		"decoration": {
			"type": "bullet"
		}
	},
	{
		"component": "text",
		"value": "through",
		"decoration": {
			"type": "bullet"
		}
	},
	{
		"component": "text",
		"value": "tobacco",
		"decoration": {
			"type": "bullet"
		}
	},
	{
		"component": "text",
		"value": "tonight",
		"decoration": {
			"type": "bullet"
		}
	},
	{
		"component": "text",
		"value": "totally",
		"decoration": {
			"type": "bullet"
		}
	},
	{
		"component": "text",
		"value": "tourist",
		"decoration": {
			"type": "bullet"
		}
	},
	{
		"component": "text",
		"value": "towards",
		"decoration": {
			"type": "bullet"
		}
	},
	{
		"component": "text",
		"value": "traffic",
		"decoration": {
			"type": "bullet"
		}
	},
	{
		"component": "text",
		"value": "tragedy",
		"decoration": {
			"type": "bullet"
		}
	},
	{
		"component": "text",
		"value": "trouble",
		"decoration": {
			"type": "bullet"
		}
	},
	{
		"component": "text",
		"value": "typical",
		"decoration": {
			"type": "bullet"
		}
	},
	{
		"component": "text",
		"value": "undergo",
		"decoration": {
			"type": "bullet"
		}
	},
	{
		"component": "text",
		"value": "uniform",
		"decoration": {
			"type": "bullet"
		}
	},
	{
		"component": "text",
		"value": "unknown",
		"decoration": {
			"type": "bullet"
		}
	},
	{
		"component": "text",
		"value": "unusual",
		"decoration": {
			"type": "bullet"
		}
	},
	{
		"component": "text",
		"value": "usually",
		"decoration": {
			"type": "bullet"
		}
	},
	{
		"component": "text",
		"value": "utility",
		"decoration": {
			"type": "bullet"
		}
	},
	{
		"component": "text",
		"value": "variety",
		"decoration": {
			"type": "bullet"
		}
	},
	{
		"component": "text",
		"value": "various",
		"decoration": {
			"type": "bullet"
		}
	},
	{
		"component": "text",
		"value": "vehicle",
		"decoration": {
			"type": "bullet"
		}
	},
	{
		"component": "text",
		"value": "venture",
		"decoration": {
			"type": "bullet"
		}
	},
	{
		"component": "text",
		"value": "version",
		"decoration": {
			"type": "bullet"
		}
	},
	{
		"component": "text",
		"value": "veteran",
		"decoration": {
			"type": "bullet"
		}
	},
	{
		"component": "text",
		"value": "victory",
		"decoration": {
			"type": "bullet"
		}
	},
	{
		"component": "text",
		"value": "village",
		"decoration": {
			"type": "bullet"
		}
	},
	{
		"component": "text",
		"value": "violate",
		"decoration": {
			"type": "bullet"
		}
	},
	{
		"component": "text",
		"value": "violent",
		"decoration": {
			"type": "bullet"
		}
	},
	{
		"component": "text",
		"value": "visible",
		"decoration": {
			"type": "bullet"
		}
	},
	{
		"component": "text",
		"value": "visitor",
		"decoration": {
			"type": "bullet"
		}
	},
	{
		"component": "text",
		"value": "warning",
		"decoration": {
			"type": "bullet"
		}
	},
	{
		"component": "text",
		"value": "wealthy",
		"decoration": {
			"type": "bullet"
		}
	},
	{
		"component": "text",
		"value": "weather",
		"decoration": {
			"type": "bullet"
		}
	},
	{
		"component": "text",
		"value": "wedding",
		"decoration": {
			"type": "bullet"
		}
	},
	{
		"component": "text",
		"value": "weekend",
		"decoration": {
			"type": "bullet"
		}
	},
	{
		"component": "text",
		"value": "welcome",
		"decoration": {
			"type": "bullet"
		}
	},
	{
		"component": "text",
		"value": "welfare",
		"decoration": {
			"type": "bullet"
		}
	},
	{
		"component": "text",
		"value": "western",
		"decoration": {
			"type": "bullet"
		}
	},
	{
		"component": "text",
		"value": "whereas",
		"decoration": {
			"type": "bullet"
		}
	},
	{
		"component": "text",
		"value": "whether",
		"decoration": {
			"type": "bullet"
		}
	},
	{
		"component": "text",
		"value": "whisper",
		"decoration": {
			"type": "bullet"
		}
	},
	{
		"component": "text",
		"value": "willing",
		"decoration": {
			"type": "bullet"
		}
	},
	{
		"component": "text",
		"value": "without",
		"decoration": {
			"type": "bullet"
		}
	},
	{
		"component": "text",
		"value": "witness",
		"decoration": {
			"type": "bullet"
		}
	},
	{
		"component": "text",
		"value": "working",
		"decoration": {
			"type": "bullet"
		}
	},
	{
		"component": "text",
		"value": "worried",
		"decoration": {
			"type": "bullet"
		}
	},
	{
		"component": "text",
		"value": "writing",
		"decoration": {
			"type": "bullet"
		}
	}
]