[
	{
		"component": "header",
		"variant": 2,
		"value": "Question 4"
	},
	{
		"component": "text",
		"value": "Make a program to print the numbers from 11 to 101. The <span style=\"\">loop</span> counter should start from <span style=\"color: #eb9371; background-color: rgba(39, 41, 43, 0.83); box-shadow: 2px 2px 2px rgba(22, 9, 1, 0.6); border-radius: 2px; padding: 2px\">156</span>."
	},
	{
		"component": "text",
		"value": "Your <span style=\"\">output</span> should be as follows ."
	},
	{
		"component": "text",
		"value": "1<br>2<br>3<br>4<br>5<br>6<br>7<br>8<br>9<br>10"
	}
]